Workbook

Sheet Parcelas Mensais
B1: CONTROLE — PARCELAS MENSAIS (Cláusula 2.2.1)
B3: DADOS DO CONTRATO
B4: Compradora: | C4: UANDA SILVA CARVALHO | J4: CPF: | K4: 066.128.216-39
B5: Imóvel: | C5: Lote 16, Quadra D — Res. Parque das Nogueiras | J5: Data Contrato: | K5: 44279
B6: Valor Total: | C6: 235695.82 | E6: Entrada: | F6: 23569.58 | H6: Saldo Mensal: | I6: 162126.24 | K6: Parcelas: | L6: 120 × dia 10 | N6: Índice: | O6: IPCA + 0,85% a.m.
B8: IDENTIFICAÇÃO | F8: VALORES (R$) | I8: IPCA | K8: CORREÇÃO ANUAL | P8: ENCARGOS ATRASO | R8: CLÁUS. 2.2.2
B9: Nº | C9: ANO | D9: MÊS | E9: DATA PGTO | F9: VLR A PAGAR | G9: VLR PAGO | H9: SALDO BASE | I9: NÚM. ÍNDICE | J9: VAR. MENSAL | K9: IPCA ACUM 12M | L9: BASE ATUAL. | M9: JUROS COMP. | N9: VALOR ATUAL. | O9: SALDO DEVEDOR | P9: MULTA 2% (R$) | Q9: JUROS MORA 0,033%/dia | R9: SALDO REM. ANUAL (R$) | S9: ANUAL PAGO (R$)
B10: ENT. | C10: 2021 | D10: MAR | E10: 44279 | F10: 23569.58 | G10: 23569.58 | H10: 162126.24 | I10: ='Índices IPCA'!C4 -> 5674.72 | L10: =H10 -> 162126.24 | N10: =H10 -> 162126.24 | O10: =H10 -> 162126.24
B11: 1 | C11: 2021 | D11: ABR | E11: 44298 | F11: =Reajustes!H4 -> 1351.05 | G11: 1392.72 | H11: =O10-IF(G11="",0,G11) -> 160733.52 | I11: ='Índices IPCA'!C5 -> 5692.31 | J11: ='Índices IPCA'!D5 -> 0.0030997124 | L11: =H11 -> 160733.52 | N11: =H11 -> 160733.52 | O11: =H11 -> 160733.52 | P11: =IF(AND(E11<>"",E11>Vencimentos!D3),F11*0.02,0) -> 0 | Q11: =IF(AND(E11<>"",E11>Vencimentos!D3),F11*0.00033*(E11-Vencimentos!D3),0) -> 0
B12: 2 | C12: 2021 | D12: MAI | E12: 44323 | F12: =Reajustes!H4 -> 1351.05 | G12: 1392.72 | H12: =O11-IF(G12="",0,G12) -> 159340.8 | I12: ='Índices IPCA'!C6 -> 5739.56 | J12: ='Índices IPCA'!D6 -> 0.0083006723 | L12: =H12 -> 159340.8 | N12: =H12 -> 159340.8 | O12: =H12 -> 159340.8 | P12: =IF(AND(E12<>"",E12>Vencimentos!D4),F12*0.02,0) -> 0 | Q12: =IF(AND(E12<>"",E12>Vencimentos!D4),F12*0.00033*(E12-Vencimentos!D4),0) -> 0
B13: 3 | C13: 2021 | D13: JUN | E13: 44357 | F13: =Reajustes!H4 -> 1351.05 | G13: 1392.72 | H13: =O12-IF(G13="",0,G13) -> 157948.08 | I13: ='Índices IPCA'!C7 -> 5769.98 | J13: ='Índices IPCA'!D7 -> 0.0053000578 | L13: =H13 -> 157948.08 | N13: =H13 -> 157948.08 | O13: =H13 -> 157948.08 | P13: =IF(AND(E13<>"",E13>Vencimentos!D5),F13*0.02,0) -> 0 | Q13: =IF(AND(E13<>"",E13>Vencimentos!D5),F13*0.00033*(E13-Vencimentos!D5),0) -> 0
B14: 4 | C14: 2021 | D14: JUL | E14: 44386 | F14: =Reajustes!H4 -> 1351.05 | G14: 1392.72 | H14: =O13-IF(G14="",0,G14) -> 156555.36 | I14: ='Índices IPCA'!C8 -> 5825.37 | J14: ='Índices IPCA'!D8 -> 0.0095996867 | L14: =H14 -> 156555.36 | N14: =H14 -> 156555.36 | O14: =H14 -> 156555.36 | P14: =IF(AND(E14<>"",E14>Vencimentos!D6),F14*0.02,0) -> 0 | Q14: =IF(AND(E14<>"",E14>Vencimentos!D6),F14*0.00033*(E14-Vencimentos!D6),0) -> 0
B15: 5 | C15: 2021 | D15: AGO | E15: 44413 | F15: =Reajustes!H4 -> 1351.05 | G15: 1392.72 | H15: =O14-IF(G15="",0,G15) -> 155162.64 | I15: ='Índices IPCA'!C9 -> 5876.05 | J15: ='Índices IPCA'!D9 -> 0.0086998766 | L15: =H15 -> 155162.64 | N15: =H15 -> 155162.64 | O15: =H15 -> 155162.64 | P15: =IF(AND(E15<>"",E15>Vencimentos!D7),F15*0.02,0) -> 0 | Q15: =IF(AND(E15<>"",E15>Vencimentos!D7),F15*0.00033*(E15-Vencimentos!D7),0) -> 0
B16: 6 | C16: 2021 | D16: SET | E16: 44449 | F16: =Reajustes!H4 -> 1351.05 | G16: 1392.72 | H16: =O15-IF(G16="",0,G16) -> 153769.92 | I16: ='Índices IPCA'!C10 -> 5944.21 | J16: ='Índices IPCA'!D10 -> 0.011599629 | L16: =H16 -> 153769.92 | N16: =H16 -> 153769.92 | O16: =H16 -> 153769.92 | P16: =IF(AND(E16<>"",E16>Vencimentos!D8),F16*0.02,0) -> 0 | Q16: =IF(AND(E16<>"",E16>Vencimentos!D8),F16*0.00033*(E16-Vencimentos!D8),0) -> 0
B17: 7 | C17: 2021 | D17: OUT | E17: 44480 | F17: =Reajustes!H4 -> 1351.05 | G17: 1392.72 | H17: =O16-IF(G17="",0,G17) -> 152377.2 | I17: ='Índices IPCA'!C11 -> 6018.51 | J17: ='Índices IPCA'!D11 -> 0.012499558 | L17: =H17 -> 152377.2 | N17: =H17 -> 152377.2 | O17: =H17 -> 152377.2 | P17: =IF(AND(E17<>"",E17>Vencimentos!D9),F17*0.02,0) -> 0 | Q17: =IF(AND(E17<>"",E17>Vencimentos!D9),F17*0.00033*(E17-Vencimentos!D9),0) -> 0
B18: 8 | C18: 2021 | D18: NOV | E18: 44510 | F18: =Reajustes!H4 -> 1351.05 | G18: 1392.72 | H18: =O17-IF(G18="",0,G18) -> 150984.48 | I18: ='Índices IPCA'!C12 -> 6075.69 | J18: ='Índices IPCA'!D12 -> 0.0095006904 | L18: =H18 -> 150984.48 | N18: =H18 -> 150984.48 | O18: =H18 -> 150984.48 | P18: =IF(AND(E18<>"",E18>Vencimentos!D10),F18*0.02,0) -> 0 | Q18: =IF(AND(E18<>"",E18>Vencimentos!D10),F18*0.00033*(E18-Vencimentos!D10),0) -> 0
B19: 9 | C19: 2021 | D19: DEZ | E19: 44540 | F19: =Reajustes!H4 -> 1351.05 | G19: 1392.72 | H19: =O18-IF(G19="",0,G19) -> 149591.76 | I19: ='Índices IPCA'!C13 -> 6120.04 | J19: ='Índices IPCA'!D13 -> 0.0072995824 | L19: =H19 -> 149591.76 | N19: =H19 -> 149591.76 | O19: =H19 -> 149591.76 | P19: =IF(AND(E19<>"",E19>Vencimentos!D11),F19*0.02,0) -> 0 | Q19: =IF(AND(E19<>"",E19>Vencimentos!D11),F19*0.00033*(E19-Vencimentos!D11),0) -> 0 | S19: 5000
B20: 10 | C20: 2022 | D20: JAN | E20: 44572 | F20: =Reajustes!H4 -> 1351.05 | G20: 1392.72 | H20: =O19-IF(G20="",0,G20) -> 148199.04 | I20: ='Índices IPCA'!C14 -> 6153.09 | J20: ='Índices IPCA'!D14 -> 0.0054002915 | L20: =H20 -> 148199.04 | N20: =H20 -> 148199.04 | O20: =H20 -> 148199.04 | P20: =IF(AND(E20<>"",E20>Vencimentos!D12),F20*0.02,0) -> 27.021 | Q20: =IF(AND(E20<>"",E20>Vencimentos!D12),F20*0.00033*(E20-Vencimentos!D12),0) -> 0.4458465
B21: 11 | C21: 2022 | D21: FEV | E21: 44602 | F21: =Reajustes!H4 -> 1351.05 | G21: 1392.72 | H21: =O20-IF(G21="",0,G21) -> 146806.32 | I21: ='Índices IPCA'!C15 -> 6215.24 | J21: ='Índices IPCA'!D15 -> 0.010100616 | L21: =H21 -> 146806.32 | N21: =H21 -> 146806.32 | O21: =H21 -> 146806.32 | P21: =IF(AND(E21<>"",E21>Vencimentos!D13),F21*0.02,0) -> 0 | Q21: =IF(AND(E21<>"",E21>Vencimentos!D13),F21*0.00033*(E21-Vencimentos!D13),0) -> 0
B22: 12 | C22: 2022 | D22: MAR | E22: 44630 | F22: =Reajustes!H4 -> 1351.05 | G22: 1392.72 | H22: =O21-IF(G22="",0,G22) -> 145413.6 | I22: ='Índices IPCA'!C16 -> 6315.93 | J22: ='Índices IPCA'!D16 -> 0.016200501 | K22: =Reajustes!F4 -> 0.11299412 | L22: =IF(K22=0,H22,H22*(1+K22)) -> 161844.48 | M22: =Reajustes!E5 -> 0.10690623 | N22: =L22*(1+M22) -> 179146.66 | O22: =N22 -> 179146.66 | P22: =IF(AND(E22<>"",E22>Vencimentos!D14),F22*0.02,0) -> 0 | Q22: =IF(AND(E22<>"",E22>Vencimentos!D14),F22*0.00033*(E22-Vencimentos!D14),0) -> 0
B23: 13 | C23: 2022 | D23: ABR | E23: 44662 | F23: =Reajustes!H5 -> 1664.4667 | G23: 1392.72 | H23: =O22-IF(G23="",0,G23) -> 177753.94 | I23: ='Índices IPCA'!C17 -> 6382.88 | J23: ='Índices IPCA'!D17 -> 0.010600181 | L23: =H23 -> 177753.94 | N23: =H23 -> 177753.94 | O23: =H23 -> 177753.94 | P23: =IF(AND(E23<>"",E23>Vencimentos!D15),F23*0.02,0) -> 0 | Q23: =IF(AND(E23<>"",E23>Vencimentos!D15),F23*0.00033*(E23-Vencimentos!D15),0) -> 0 | R23: =Reajustes!I21 -> 45000
B24: 14 | C24: 2022 | D24: MAI | E24: 44691 | F24: =Reajustes!H5 -> 1664.4667 | G24: 1392.72 | H24: =O23-IF(G24="",0,G24) -> 176361.22 | I24: ='Índices IPCA'!C18 -> 6412.88 | J24: ='Índices IPCA'!D18 -> 0.0047000727 | L24: =H24 -> 176361.22 | N24: =H24 -> 176361.22 | O24: =H24 -> 176361.22 | P24: =IF(AND(E24<>"",E24>Vencimentos!D16),F24*0.02,0) -> 0 | Q24: =IF(AND(E24<>"",E24>Vencimentos!D16),F24*0.00033*(E24-Vencimentos!D16),0) -> 0
B25: 15 | C25: 2022 | D25: JUN | E25: 44726 | F25: =Reajustes!H5 -> 1664.4667 | G25: 1392.72 | H25: =O24-IF(G25="",0,G25) -> 174968.5 | I25: ='Índices IPCA'!C19 -> 6455.85 | J25: ='Índices IPCA'!D19 -> 0.0067005776 | L25: =H25 -> 174968.5 | N25: =H25 -> 174968.5 | O25: =H25 -> 174968.5 | P25: =IF(AND(E25<>"",E25>Vencimentos!D17),F25*0.02,0) -> 33.289335 | Q25: =IF(AND(E25<>"",E25>Vencimentos!D17),F25*0.00033*(E25-Vencimentos!D17),0) -> 2.1970961
B26: 16 | C26: 2022 | D26: JUL | E26: 44783 | F26: =Reajustes!H5 -> 1664.4667 | G26: 1392.72 | H26: =O25-IF(G26="",0,G26) -> 173575.78 | I26: ='Índices IPCA'!C20 -> 6411.95 | J26: ='Índices IPCA'!D20 -> -0.0068000341 | L26: =H26 -> 173575.78 | N26: =H26 -> 173575.78 | O26: =H26 -> 173575.78 | P26: =IF(AND(E26<>"",E26>Vencimentos!D18),F26*0.02,0) -> 33.289335 | Q26: =IF(AND(E26<>"",E26>Vencimentos!D18),F26*0.00033*(E26-Vencimentos!D18),0) -> 16.478221
B27: 17 | C27: 2022 | D27: AGO | E27: 44844 | F27: =Reajustes!H5 -> 1664.4667 | G27: 1392.72 | H27: =O26-IF(G27="",0,G27) -> 172183.06 | I27: ='Índices IPCA'!C21 -> 6388.87 | J27: ='Índices IPCA'!D21 -> -0.003599529 | L27: =H27 -> 172183.06 | N27: =H27 -> 172183.06 | O27: =H27 -> 172183.06 | P27: =IF(AND(E27<>"",E27>Vencimentos!D19),F27*0.02,0) -> 33.289335 | Q27: =IF(AND(E27<>"",E27>Vencimentos!D19),F27*0.00033*(E27-Vencimentos!D19),0) -> 33.505716
B28: 18 | C28: 2022 | D28: SET | E28: 44876 | F28: =Reajustes!H5 -> 1664.4667 | G28: 1392.72 | H28: =O27-IF(G28="",0,G28) -> 170790.34 | I28: ='Índices IPCA'!C22 -> 6370.34 | J28: ='Índices IPCA'!D22 -> -0.0029003564 | L28: =H28 -> 170790.34 | N28: =H28 -> 170790.34 | O28: =H28 -> 170790.34 | P28: =IF(AND(E28<>"",E28>Vencimentos!D20),F28*0.02,0) -> 33.289335 | Q28: =IF(AND(E28<>"",E28>Vencimentos!D20),F28*0.00033*(E28-Vencimentos!D20),0) -> 32.956442
B29: 19 | C29: 2022 | D29: OUT | E29: 44908 | F29: =Reajustes!H5 -> 1664.4667 | G29: 1351.05 | H29: =O28-IF(G29="",0,G29) -> 169439.29 | I29: ='Índices IPCA'!C23 -> 6407.93 | J29: ='Índices IPCA'!D23 -> 0.0059007839 | L29: =H29 -> 169439.29 | N29: =H29 -> 169439.29 | O29: =H29 -> 169439.29 | P29: =IF(AND(E29<>"",E29>Vencimentos!D21),F29*0.02,0) -> 33.289335 | Q29: =IF(AND(E29<>"",E29>Vencimentos!D21),F29*0.00033*(E29-Vencimentos!D21),0) -> 35.153538 | S29: 5000
B30: 20 | C30: 2022 | D30: NOV | E30: 44937 | F30: =Reajustes!H5 -> 1664.4667 | G30: 1392.72 | H30: =O29-IF(G30="",0,G30) -> 168046.57 | I30: ='Índices IPCA'!C24 -> 6434.2 | J30: ='Índices IPCA'!D24 -> 0.0040996078 | L30: =H30 -> 168046.57 | N30: =H30 -> 168046.57 | O30: =H30 -> 168046.57 | P30: =IF(AND(E30<>"",E30>Vencimentos!D22),F30*0.02,0) -> 33.289335 | Q30: =IF(AND(E30<>"",E30>Vencimentos!D22),F30*0.00033*(E30-Vencimentos!D22),0) -> 34.05499
B31: 21 | C31: 2022 | D31: DEZ | E31: 44968 | F31: =Reajustes!H5 -> 1664.4667 | G31: 1500 | H31: =O30-IF(G31="",0,G31) -> 166546.57 | I31: ='Índices IPCA'!C25 -> 6474.09 | J31: ='Índices IPCA'!D25 -> 0.0061996829 | L31: =H31 -> 166546.57 | N31: =H31 -> 166546.57 | O31: =H31 -> 166546.57 | P31: =IF(AND(E31<>"",E31>Vencimentos!D23),F31*0.02,0) -> 33.289335 | Q31: =IF(AND(E31<>"",E31>Vencimentos!D23),F31*0.00033*(E31-Vencimentos!D23),0) -> 33.505716
B32: 22 | C32: 2023 | D32: JAN | E32: 44998 | F32: =Reajustes!H5 -> 1664.4667 | G32: 2000 | H32: =O31-IF(G32="",0,G32) -> 164546.57 | I32: ='Índices IPCA'!C26 -> 6508.4 | J32: ='Índices IPCA'!D26 -> 0.0052995865 | L32: =H32 -> 164546.57 | N32: =H32 -> 164546.57 | O32: =H32 -> 164546.57 | P32: =IF(AND(E32<>"",E32>Vencimentos!D24),F32*0.02,0) -> 33.289335 | Q32: =IF(AND(E32<>"",E32>Vencimentos!D24),F32*0.00033*(E32-Vencimentos!D24),0) -> 34.05499
B33: 23 | C33: 2023 | D33: FEV | E33: 45028 | F33: =Reajustes!H5 -> 1664.4667 | G33: 1500 | H33: =O32-IF(G33="",0,G33) -> 163046.57 | I33: ='Índices IPCA'!C27 -> 6563.07 | J33: ='Índices IPCA'!D27 -> 0.008399914 | L33: =H33 -> 163046.57 | N33: =H33 -> 163046.57 | O33: =H33 -> 163046.57 | P33: =IF(AND(E33<>"",E33>Vencimentos!D25),F33*0.02,0) -> 33.289335 | Q33: =IF(AND(E33<>"",E33>Vencimentos!D25),F33*0.00033*(E33-Vencimentos!D25),0) -> 33.505716
B34: 24 | C34: 2023 | D34: MAR | E34: 45056 | F34: =Reajustes!H5 -> 1664.4667 | G34: 1500 | H34: =O33-IF(G34="",0,G34) -> 161546.57 | I34: ='Índices IPCA'!C28 -> 6609.67 | J34: ='Índices IPCA'!D28 -> 0.0071003357 | K34: =Reajustes!F5 -> 0.046507799 | L34: =IF(K34=0,H34,H34*(1+K34)) -> 169059.75 | M34: =Reajustes!E6 -> 0.10690623 | N34: =L34*(1+M34) -> 187133.29 | O34: =N34 -> 187133.29 | P34: =IF(AND(E34<>"",E34>Vencimentos!D26),F34*0.02,0) -> 33.289335 | Q34: =IF(AND(E34<>"",E34>Vencimentos!D26),F34*0.00033*(E34-Vencimentos!D26),0) -> 33.505716
B35: 25 | C35: 2023 | D35: ABR | E35: 45085 | F35: =Reajustes!H6 -> 1928.095 | G35: 1500 | H35: =O34-IF(G35="",0,G35) -> 185633.29 | I35: ='Índices IPCA'!C29 -> 6649.99 | J35: ='Índices IPCA'!D29 -> 0.0061001533 | L35: =H35 -> 185633.29 | N35: =H35 -> 185633.29 | O35: =H35 -> 185633.29 | P35: =IF(AND(E35<>"",E35>Vencimentos!D27),F35*0.02,0) -> 38.561899 | Q35: =IF(AND(E35<>"",E35>Vencimentos!D27),F35*0.00033*(E35-Vencimentos!D27),0) -> 37.540009 | R35: =Reajustes!I22 -> 46335.44
B36: 26 | C36: 2023 | D36: MAI | E36: 45118 | F36: =Reajustes!H6 -> 1928.095 | G36: 1500 | H36: =O35-IF(G36="",0,G36) -> 184133.29 | I36: ='Índices IPCA'!C30 -> 6665.28 | J36: ='Índices IPCA'!D30 -> 0.0022992516 | L36: =H36 -> 184133.29 | N36: =H36 -> 184133.29 | O36: =H36 -> 184133.29 | P36: =IF(AND(E36<>"",E36>Vencimentos!D28),F36*0.02,0) -> 38.561899 | Q36: =IF(AND(E36<>"",E36>Vencimentos!D28),F36*0.00033*(E36-Vencimentos!D28),0) -> 39.448823
B37: 27 | C37: 2023 | D37: JUN | E37: 45148 | F37: =Reajustes!H6 -> 1928.095 | G37: 1500 | H37: =O36-IF(G37="",0,G37) -> 182633.29 | I37: ='Índices IPCA'!C31 -> 6659.95 | J37: ='Índices IPCA'!D31 -> -0.00079966633 | L37: =H37 -> 182633.29 | N37: =H37 -> 182633.29 | O37: =H37 -> 182633.29 | P37: =IF(AND(E37<>"",E37>Vencimentos!D29),F37*0.02,0) -> 38.561899 | Q37: =IF(AND(E37<>"",E37>Vencimentos!D29),F37*0.00033*(E37-Vencimentos!D29),0) -> 37.540009
B38: 28 | C38: 2023 | D38: JUL | E38: 45182 | F38: =Reajustes!H6 -> 1928.095 | G38: 1500 | H38: =O37-IF(G38="",0,G38) -> 181133.29 | I38: ='Índices IPCA'!C32 -> 6667.94 | J38: ='Índices IPCA'!D32 -> 0.0011997087 | L38: =H38 -> 181133.29 | N38: =H38 -> 181133.29 | O38: =H38 -> 181133.29 | P38: =IF(AND(E38<>"",E38>Vencimentos!D30),F38*0.02,0) -> 38.561899 | Q38: =IF(AND(E38<>"",E38>Vencimentos!D30),F38*0.00033*(E38-Vencimentos!D30),0) -> 41.357637
B39: 29 | C39: 2023 | D39: AGO | F39: =Reajustes!H6 -> 1928.095 | H39: =O38-IF(G39="",0,G39) -> 181133.29 | I39: ='Índices IPCA'!C33 -> 6683.28 | J39: ='Índices IPCA'!D33 -> 0.0023005606 | L39: =H39 -> 181133.29 | N39: =H39 -> 181133.29 | O39: =H39 -> 181133.29 | P39: =IF(AND(E39<>"",E39>Vencimentos!D31),F39*0.02,0) -> 0 | Q39: =IF(AND(E39<>"",E39>Vencimentos!D31),F39*0.00033*(E39-Vencimentos!D31),0) -> 0
B40: 30 | C40: 2023 | D40: SET | F40: =Reajustes!H6 -> 1928.095 | H40: =O39-IF(G40="",0,G40) -> 181133.29 | I40: ='Índices IPCA'!C34 -> 6700.66 | J40: ='Índices IPCA'!D34 -> 0.0026005195 | L40: =H40 -> 181133.29 | N40: =H40 -> 181133.29 | O40: =H40 -> 181133.29 | P40: =IF(AND(E40<>"",E40>Vencimentos!D32),F40*0.02,0) -> 0 | Q40: =IF(AND(E40<>"",E40>Vencimentos!D32),F40*0.00033*(E40-Vencimentos!D32),0) -> 0
B41: 31 | C41: 2023 | D41: OUT | F41: =Reajustes!H6 -> 1928.095 | H41: =O40-IF(G41="",0,G41) -> 181133.29 | I41: ='Índices IPCA'!C35 -> 6716.74 | J41: ='Índices IPCA'!D35 -> 0.0023997636 | L41: =H41 -> 181133.29 | N41: =H41 -> 181133.29 | O41: =H41 -> 181133.29 | P41: =IF(AND(E41<>"",E41>Vencimentos!D33),F41*0.02,0) -> 0 | Q41: =IF(AND(E41<>"",E41>Vencimentos!D33),F41*0.00033*(E41-Vencimentos!D33),0) -> 0
B42: 32 | C42: 2023 | D42: NOV | F42: =Reajustes!H6 -> 1928.095 | H42: =O41-IF(G42="",0,G42) -> 181133.29 | I42: ='Índices IPCA'!C36 -> 6735.55 | J42: ='Índices IPCA'!D36 -> 0.0028004657 | L42: =H42 -> 181133.29 | N42: =H42 -> 181133.29 | O42: =H42 -> 181133.29 | P42: =IF(AND(E42<>"",E42>Vencimentos!D34),F42*0.02,0) -> 0 | Q42: =IF(AND(E42<>"",E42>Vencimentos!D34),F42*0.00033*(E42-Vencimentos!D34),0) -> 0
B43: 33 | C43: 2023 | D43: DEZ | F43: =Reajustes!H6 -> 1928.095 | H43: =O42-IF(G43="",0,G43) -> 181133.29 | I43: ='Índices IPCA'!C37 -> 6773.27 | J43: ='Índices IPCA'!D37 -> 0.0056001366 | L43: =H43 -> 181133.29 | N43: =H43 -> 181133.29 | O43: =H43 -> 181133.29 | P43: =IF(AND(E43<>"",E43>Vencimentos!D35),F43*0.02,0) -> 0 | Q43: =IF(AND(E43<>"",E43>Vencimentos!D35),F43*0.00033*(E43-Vencimentos!D35),0) -> 0
B44: 34 | C44: 2024 | D44: JAN | F44: =Reajustes!H6 -> 1928.095 | H44: =O43-IF(G44="",0,G44) -> 181133.29 | I44: ='Índices IPCA'!C38 -> 6801.72 | J44: ='Índices IPCA'!D38 -> 0.0042003346 | L44: =H44 -> 181133.29 | N44: =H44 -> 181133.29 | O44: =H44 -> 181133.29 | P44: =IF(AND(E44<>"",E44>Vencimentos!D36),F44*0.02,0) -> 0 | Q44: =IF(AND(E44<>"",E44>Vencimentos!D36),F44*0.00033*(E44-Vencimentos!D36),0) -> 0
B45: 35 | C45: 2024 | D45: FEV | F45: =Reajustes!H6 -> 1928.095 | H45: =O44-IF(G45="",0,G45) -> 181133.29 | I45: ='Índices IPCA'!C39 -> 6858.17 | J45: ='Índices IPCA'!D39 -> 0.0082993713 | L45: =H45 -> 181133.29 | N45: =H45 -> 181133.29 | O45: =H45 -> 181133.29 | P45: =IF(AND(E45<>"",E45>Vencimentos!D37),F45*0.02,0) -> 0 | Q45: =IF(AND(E45<>"",E45>Vencimentos!D37),F45*0.00033*(E45-Vencimentos!D37),0) -> 0
B46: 36 | C46: 2024 | D46: MAR | F46: =Reajustes!H6 -> 1928.095 | H46: =O45-IF(G46="",0,G46) -> 181133.29 | I46: ='Índices IPCA'!C40 -> 6869.14 | J46: ='Índices IPCA'!D40 -> 0.0015995521 | K46: =Reajustes!F6 -> 0.03925612 | L46: =IF(K46=0,H46,H46*(1+K46)) -> 188243.88 | M46: =Reajustes!E7 -> 0.10690623 | N46: =L46*(1+M46) -> 208368.32 | O46: =N46 -> 208368.32 | P46: =IF(AND(E46<>"",E46>Vencimentos!D38),F46*0.02,0) -> 0 | Q46: =IF(AND(E46<>"",E46>Vencimentos!D38),F46*0.00033*(E46-Vencimentos!D38),0) -> 0
B47: 37 | C47: 2024 | D47: ABR | F47: =Reajustes!H7 -> 2218.0015 | H47: =O46-IF(G47="",0,G47) -> 208368.32 | I47: ='Índices IPCA'!C41 -> 6895.24 | J47: ='Índices IPCA'!D41 -> 0.0037996023 | L47: =H47 -> 208368.32 | N47: =H47 -> 208368.32 | O47: =H47 -> 208368.32 | P47: =IF(AND(E47<>"",E47>Vencimentos!D39),F47*0.02,0) -> 0 | Q47: =IF(AND(E47<>"",E47>Vencimentos!D39),F47*0.00033*(E47-Vencimentos!D39),0) -> 0 | R47: =Reajustes!I23 -> 53302.394
B48: 38 | C48: 2024 | D48: MAI | F48: =Reajustes!H7 -> 2218.0015 | H48: =O47-IF(G48="",0,G48) -> 208368.32 | I48: ='Índices IPCA'!C42 -> 6926.96 | J48: ='Índices IPCA'!D42 -> 0.004600275 | L48: =H48 -> 208368.32 | N48: =H48 -> 208368.32 | O48: =H48 -> 208368.32 | P48: =IF(AND(E48<>"",E48>Vencimentos!D40),F48*0.02,0) -> 0 | Q48: =IF(AND(E48<>"",E48>Vencimentos!D40),F48*0.00033*(E48-Vencimentos!D40),0) -> 0
B49: 39 | C49: 2024 | D49: JUN | F49: =Reajustes!H7 -> 2218.0015 | H49: =O48-IF(G49="",0,G49) -> 208368.32 | I49: ='Índices IPCA'!C43 -> 6941.51 | J49: ='Índices IPCA'!D43 -> 0.0021004885 | L49: =H49 -> 208368.32 | N49: =H49 -> 208368.32 | O49: =H49 -> 208368.32 | P49: =IF(AND(E49<>"",E49>Vencimentos!D41),F49*0.02,0) -> 0 | Q49: =IF(AND(E49<>"",E49>Vencimentos!D41),F49*0.00033*(E49-Vencimentos!D41),0) -> 0
B50: 40 | C50: 2024 | D50: JUL | F50: =Reajustes!H7 -> 2218.0015 | H50: =O49-IF(G50="",0,G50) -> 208368.32 | I50: ='Índices IPCA'!C44 -> 6967.89 | J50: ='Índices IPCA'!D44 -> 0.0038003259 | L50: =H50 -> 208368.32 | N50: =H50 -> 208368.32 | O50: =H50 -> 208368.32 | P50: =IF(AND(E50<>"",E50>Vencimentos!D42),F50*0.02,0) -> 0 | Q50: =IF(AND(E50<>"",E50>Vencimentos!D42),F50*0.00033*(E50-Vencimentos!D42),0) -> 0
B51: 41 | C51: 2024 | D51: AGO | F51: =Reajustes!H7 -> 2218.0015 | H51: =O50-IF(G51="",0,G51) -> 208368.32 | I51: ='Índices IPCA'!C45 -> 6966.5 | J51: ='Índices IPCA'!D45 -> -0.0001994865 | L51: =H51 -> 208368.32 | N51: =H51 -> 208368.32 | O51: =H51 -> 208368.32 | P51: =IF(AND(E51<>"",E51>Vencimentos!D43),F51*0.02,0) -> 0 | Q51: =IF(AND(E51<>"",E51>Vencimentos!D43),F51*0.00033*(E51-Vencimentos!D43),0) -> 0
B52: 42 | C52: 2024 | D52: SET | F52: =Reajustes!H7 -> 2218.0015 | H52: =O51-IF(G52="",0,G52) -> 208368.32 | I52: ='Índices IPCA'!C46 -> 6997.15 | J52: ='Índices IPCA'!D46 -> 0.0043996268 | L52: =H52 -> 208368.32 | N52: =H52 -> 208368.32 | O52: =H52 -> 208368.32 | P52: =IF(AND(E52<>"",E52>Vencimentos!D44),F52*0.02,0) -> 0 | Q52: =IF(AND(E52<>"",E52>Vencimentos!D44),F52*0.00033*(E52-Vencimentos!D44),0) -> 0
B53: 43 | C53: 2024 | D53: OUT | F53: =Reajustes!H7 -> 2218.0015 | H53: =O52-IF(G53="",0,G53) -> 208368.32 | I53: ='Índices IPCA'!C47 -> 7036.33 | J53: ='Índices IPCA'!D47 -> 0.0055994226 | L53: =H53 -> 208368.32 | N53: =H53 -> 208368.32 | O53: =H53 -> 208368.32 | P53: =IF(AND(E53<>"",E53>Vencimentos!D45),F53*0.02,0) -> 0 | Q53: =IF(AND(E53<>"",E53>Vencimentos!D45),F53*0.00033*(E53-Vencimentos!D45),0) -> 0
B54: 44 | C54: 2024 | D54: NOV | F54: =Reajustes!H7 -> 2218.0015 | H54: =O53-IF(G54="",0,G54) -> 208368.32 | I54: ='Índices IPCA'!C48 -> 7063.77 | J54: ='Índices IPCA'!D48 -> 0.0038997602 | L54: =H54 -> 208368.32 | N54: =H54 -> 208368.32 | O54: =H54 -> 208368.32 | P54: =IF(AND(E54<>"",E54>Vencimentos!D46),F54*0.02,0) -> 0 | Q54: =IF(AND(E54<>"",E54>Vencimentos!D46),F54*0.00033*(E54-Vencimentos!D46),0) -> 0
B55: 45 | C55: 2024 | D55: DEZ | F55: =Reajustes!H7 -> 2218.0015 | H55: =O54-IF(G55="",0,G55) -> 208368.32 | I55: ='Índices IPCA'!C49 -> 7100.5 | J55: ='Índices IPCA'!D49 -> 0.0051997729 | L55: =H55 -> 208368.32 | N55: =H55 -> 208368.32 | O55: =H55 -> 208368.32 | P55: =IF(AND(E55<>"",E55>Vencimentos!D47),F55*0.02,0) -> 0 | Q55: =IF(AND(E55<>"",E55>Vencimentos!D47),F55*0.00033*(E55-Vencimentos!D47),0) -> 0
B56: 46 | C56: 2025 | D56: JAN | F56: =Reajustes!H7 -> 2218.0015 | H56: =O55-IF(G56="",0,G56) -> 208368.32 | I56: ='Índices IPCA'!C50 -> 7111.86 | J56: ='Índices IPCA'!D50 -> 0.0015998873 | L56: =H56 -> 208368.32 | N56: =H56 -> 208368.32 | O56: =H56 -> 208368.32 | P56: =IF(AND(E56<>"",E56>Vencimentos!D48),F56*0.02,0) -> 0 | Q56: =IF(AND(E56<>"",E56>Vencimentos!D48),F56*0.00033*(E56-Vencimentos!D48),0) -> 0
B57: 47 | C57: 2025 | D57: FEV | F57: =Reajustes!H7 -> 2218.0015 | H57: =O56-IF(G57="",0,G57) -> 208368.32 | I57: ='Índices IPCA'!C51 -> 7205.03 | J57: ='Índices IPCA'!D51 -> 0.013100652 | L57: =H57 -> 208368.32 | N57: =H57 -> 208368.32 | O57: =H57 -> 208368.32 | P57: =IF(AND(E57<>"",E57>Vencimentos!D49),F57*0.02,0) -> 0 | Q57: =IF(AND(E57<>"",E57>Vencimentos!D49),F57*0.00033*(E57-Vencimentos!D49),0) -> 0
B58: 48 | C58: 2025 | D58: MAR | F58: =Reajustes!H7 -> 2218.0015 | H58: =O57-IF(G58="",0,G58) -> 208368.32 | I58: ='Índices IPCA'!C52 -> 7245.38 | J58: ='Índices IPCA'!D52 -> 0.0056002543 | K58: =Reajustes!F7 -> 0.054772504 | L58: =IF(K58=0,H58,H58*(1+K58)) -> 219781.18 | M58: =Reajustes!E8 -> 0.10690623 | N58: =L58*(1+M58) -> 243277.16 | O58: =N58 -> 243277.16 | P58: =IF(AND(E58<>"",E58>Vencimentos!D50),F58*0.02,0) -> 0 | Q58: =IF(AND(E58<>"",E58>Vencimentos!D50),F58*0.00033*(E58-Vencimentos!D50),0) -> 0
B59: 49 | C59: 2025 | D59: ABR | F59: =Reajustes!H8 -> 2589.5928 | H59: =O58-IF(G59="",0,G59) -> 243277.16 | I59: ='Índices IPCA'!C53 -> 7276.53 | J59: ='Índices IPCA'!D53 -> 0.0042992914 | L59: =H59 -> 243277.16 | N59: =H59 -> 243277.16 | O59: =H59 -> 243277.16 | P59: =IF(AND(E59<>"",E59>Vencimentos!D51),F59*0.02,0) -> 0 | Q59: =IF(AND(E59<>"",E59>Vencimentos!D51),F59*0.00033*(E59-Vencimentos!D51),0) -> 0 | R59: =Reajustes!I24 -> 62232.37
B60: 50 | C60: 2025 | D60: MAI | F60: =Reajustes!H8 -> 2589.5928 | H60: =O59-IF(G60="",0,G60) -> 243277.16 | I60: ='Índices IPCA'!C54 -> 7295.45 | J60: ='Índices IPCA'!D54 -> 0.0026001405 | L60: =H60 -> 243277.16 | N60: =H60 -> 243277.16 | O60: =H60 -> 243277.16 | P60: =IF(AND(E60<>"",E60>Vencimentos!D52),F60*0.02,0) -> 0 | Q60: =IF(AND(E60<>"",E60>Vencimentos!D52),F60*0.00033*(E60-Vencimentos!D52),0) -> 0
B61: 51 | C61: 2025 | D61: JUN | F61: =Reajustes!H8 -> 2589.5928 | H61: =O60-IF(G61="",0,G61) -> 243277.16 | I61: ='Índices IPCA'!C55 -> 7312.96 | J61: ='Índices IPCA'!D55 -> 0.0024001261 | L61: =H61 -> 243277.16 | N61: =H61 -> 243277.16 | O61: =H61 -> 243277.16 | P61: =IF(AND(E61<>"",E61>Vencimentos!D53),F61*0.02,0) -> 0 | Q61: =IF(AND(E61<>"",E61>Vencimentos!D53),F61*0.00033*(E61-Vencimentos!D53),0) -> 0
B62: 52 | C62: 2025 | D62: JUL | F62: =Reajustes!H8 -> 2589.5928 | H62: =O61-IF(G62="",0,G62) -> 243277.16 | I62: ='Índices IPCA'!C56 -> 7331.97 | J62: ='Índices IPCA'!D56 -> 0.0025994946 | L62: =H62 -> 243277.16 | N62: =H62 -> 243277.16 | O62: =H62 -> 243277.16 | P62: =IF(AND(E62<>"",E62>Vencimentos!D54),F62*0.02,0) -> 0 | Q62: =IF(AND(E62<>"",E62>Vencimentos!D54),F62*0.00033*(E62-Vencimentos!D54),0) -> 0
B63: 53 | C63: 2025 | D63: AGO | F63: =Reajustes!H8 -> 2589.5928 | H63: =O62-IF(G63="",0,G63) -> 243277.16 | I63: ='Índices IPCA'!C57 -> 7323.91 | J63: ='Índices IPCA'!D57 -> -0.0010992953 | L63: =H63 -> 243277.16 | N63: =H63 -> 243277.16 | O63: =H63 -> 243277.16 | P63: =IF(AND(E63<>"",E63>Vencimentos!D55),F63*0.02,0) -> 0 | Q63: =IF(AND(E63<>"",E63>Vencimentos!D55),F63*0.00033*(E63-Vencimentos!D55),0) -> 0
B64: 54 | C64: 2025 | D64: SET | F64: =Reajustes!H8 -> 2589.5928 | H64: =O63-IF(G64="",0,G64) -> 243277.16 | I64: ='Índices IPCA'!C58 -> 7359.06 | J64: ='Índices IPCA'!D58 -> 0.004799349 | L64: =H64 -> 243277.16 | N64: =H64 -> 243277.16 | O64: =H64 -> 243277.16 | P64: =IF(AND(E64<>"",E64>Vencimentos!D56),F64*0.02,0) -> 0 | Q64: =IF(AND(E64<>"",E64>Vencimentos!D56),F64*0.00033*(E64-Vencimentos!D56),0) -> 0
B65: 55 | C65: 2025 | D65: OUT | F65: =Reajustes!H8 -> 2589.5928 | H65: =O64-IF(G65="",0,G65) -> 243277.16 | I65: ='Índices IPCA'!C59 -> 7365.69 | J65: ='Índices IPCA'!D59 -> 0.00090093028 | L65: =H65 -> 243277.16 | N65: =H65 -> 243277.16 | O65: =H65 -> 243277.16 | P65: =IF(AND(E65<>"",E65>Vencimentos!D57),F65*0.02,0) -> 0 | Q65: =IF(AND(E65<>"",E65>Vencimentos!D57),F65*0.00033*(E65-Vencimentos!D57),0) -> 0
B66: 56 | C66: 2025 | D66: NOV | F66: =Reajustes!H8 -> 2589.5928 | H66: =O65-IF(G66="",0,G66) -> 243277.16 | I66: ='Índices IPCA'!C60 -> 7378.94 | J66: ='Índices IPCA'!D60 -> 0.001798881 | L66: =H66 -> 243277.16 | N66: =H66 -> 243277.16 | O66: =H66 -> 243277.16 | P66: =IF(AND(E66<>"",E66>Vencimentos!D58),F66*0.02,0) -> 0 | Q66: =IF(AND(E66<>"",E66>Vencimentos!D58),F66*0.00033*(E66-Vencimentos!D58),0) -> 0
B67: 57 | C67: 2025 | D67: DEZ | F67: =Reajustes!H8 -> 2589.5928 | H67: =O66-IF(G67="",0,G67) -> 243277.16 | I67: ='Índices IPCA'!C61 -> 7403.29 | J67: ='Índices IPCA'!D61 -> 0.003299932 | L67: =H67 -> 243277.16 | N67: =H67 -> 243277.16 | O67: =H67 -> 243277.16 | P67: =IF(AND(E67<>"",E67>Vencimentos!D59),F67*0.02,0) -> 0 | Q67: =IF(AND(E67<>"",E67>Vencimentos!D59),F67*0.00033*(E67-Vencimentos!D59),0) -> 0
B68: 58 | C68: 2026 | D68: JAN | F68: =Reajustes!H8 -> 2589.5928 | H68: =O67-IF(G68="",0,G68) -> 243277.16 | I68: ='Índices IPCA'!C62 -> 7427.73 | J68: ='Índices IPCA'!D62 -> 0.003301235 | L68: =H68 -> 243277.16 | N68: =H68 -> 243277.16 | O68: =H68 -> 243277.16 | P68: =IF(AND(E68<>"",E68>Vencimentos!D60),F68*0.02,0) -> 0 | Q68: =IF(AND(E68<>"",E68>Vencimentos!D60),F68*0.00033*(E68-Vencimentos!D60),0) -> 0
B69: 59 | C69: 2026 | D69: FEV | F69: =Reajustes!H8 -> 2589.5928 | H69: =O68-IF(G69="",0,G69) -> 243277.16 | I69: ='Índices IPCA'!C63 -> 7479.72 | J69: ='Índices IPCA'!D63 -> 0.0069994467 | L69: =H69 -> 243277.16 | N69: =H69 -> 243277.16 | O69: =H69 -> 243277.16 | P69: =IF(AND(E69<>"",E69>Vencimentos!D61),F69*0.02,0) -> 0 | Q69: =IF(AND(E69<>"",E69>Vencimentos!D61),F69*0.00033*(E69-Vencimentos!D61),0) -> 0
B70: 60 | C70: 2026 | D70: MAR | F70: =Reajustes!H8 -> 2589.5928 | H70: =O69-IF(G70="",0,G70) -> 243277.16 | I70: ='Índices IPCA'!C64 -> 7545.54 | J70: ='Índices IPCA'!D64 -> 0.0087997946 | K70: =Reajustes!F8 -> 0.041427779 | L70: =IF(K70=0,H70,H70*(1+K70)) -> 253355.59 | M70: =Reajustes!E9 -> 0.10690623 | N70: =L70*(1+M70) -> 280440.88 | O70: =N70 -> 280440.88 | P70: =IF(AND(E70<>"",E70>Vencimentos!D62),F70*0.02,0) -> 0 | Q70: =IF(AND(E70<>"",E70>Vencimentos!D62),F70*0.00033*(E70-Vencimentos!D62),0) -> 0
B71: 61 | C71: 2026 | D71: ABR | F71: =Reajustes!H9 -> 2985.1865 | H71: =O70-IF(G71="",0,G71) -> 280440.88 | L71: =H71 -> 280440.88 | N71: =H71 -> 280440.88 | O71: =H71 -> 280440.88 | P71: =IF(AND(E71<>"",E71>Vencimentos!D63),F71*0.02,0) -> 0 | Q71: =IF(AND(E71<>"",E71>Vencimentos!D63),F71*0.00033*(E71-Vencimentos!D63),0) -> 0 | R71: =Reajustes!I25 -> 71739.167
B72: 62 | C72: 2026 | D72: MAI | F72: =Reajustes!H9 -> 2985.1865 | H72: =O71-IF(G72="",0,G72) -> 280440.88 | L72: =H72 -> 280440.88 | N72: =H72 -> 280440.88 | O72: =H72 -> 280440.88 | P72: =IF(AND(E72<>"",E72>Vencimentos!D64),F72*0.02,0) -> 0 | Q72: =IF(AND(E72<>"",E72>Vencimentos!D64),F72*0.00033*(E72-Vencimentos!D64),0) -> 0
B73: 63 | C73: 2026 | D73: JUN | F73: =Reajustes!H9 -> 2985.1865 | H73: =O72-IF(G73="",0,G73) -> 280440.88 | L73: =H73 -> 280440.88 | N73: =H73 -> 280440.88 | O73: =H73 -> 280440.88 | P73: =IF(AND(E73<>"",E73>Vencimentos!D65),F73*0.02,0) -> 0 | Q73: =IF(AND(E73<>"",E73>Vencimentos!D65),F73*0.00033*(E73-Vencimentos!D65),0) -> 0
B74: 64 | C74: 2026 | D74: JUL | F74: =Reajustes!H9 -> 2985.1865 | H74: =O73-IF(G74="",0,G74) -> 280440.88 | L74: =H74 -> 280440.88 | N74: =H74 -> 280440.88 | O74: =H74 -> 280440.88 | P74: =IF(AND(E74<>"",E74>Vencimentos!D66),F74*0.02,0) -> 0 | Q74: =IF(AND(E74<>"",E74>Vencimentos!D66),F74*0.00033*(E74-Vencimentos!D66),0) -> 0
B75: 65 | C75: 2026 | D75: AGO | F75: =Reajustes!H9 -> 2985.1865 | H75: =O74-IF(G75="",0,G75) -> 280440.88 | L75: =H75 -> 280440.88 | N75: =H75 -> 280440.88 | O75: =H75 -> 280440.88 | P75: =IF(AND(E75<>"",E75>Vencimentos!D67),F75*0.02,0) -> 0 | Q75: =IF(AND(E75<>"",E75>Vencimentos!D67),F75*0.00033*(E75-Vencimentos!D67),0) -> 0
B76: 66 | C76: 2026 | D76: SET | F76: =Reajustes!H9 -> 2985.1865 | H76: =O75-IF(G76="",0,G76) -> 280440.88 | L76: =H76 -> 280440.88 | N76: =H76 -> 280440.88 | O76: =H76 -> 280440.88 | P76: =IF(AND(E76<>"",E76>Vencimentos!D68),F76*0.02,0) -> 0 | Q76: =IF(AND(E76<>"",E76>Vencimentos!D68),F76*0.00033*(E76-Vencimentos!D68),0) -> 0
B77: 67 | C77: 2026 | D77: OUT | F77: =Reajustes!H9 -> 2985.1865 | H77: =O76-IF(G77="",0,G77) -> 280440.88 | L77: =H77 -> 280440.88 | N77: =H77 -> 280440.88 | O77: =H77 -> 280440.88 | P77: =IF(AND(E77<>"",E77>Vencimentos!D69),F77*0.02,0) -> 0 | Q77: =IF(AND(E77<>"",E77>Vencimentos!D69),F77*0.00033*(E77-Vencimentos!D69),0) -> 0
B78: 68 | C78: 2026 | D78: NOV | F78: =Reajustes!H9 -> 2985.1865 | H78: =O77-IF(G78="",0,G78) -> 280440.88 | L78: =H78 -> 280440.88 | N78: =H78 -> 280440.88 | O78: =H78 -> 280440.88 | P78: =IF(AND(E78<>"",E78>Vencimentos!D70),F78*0.02,0) -> 0 | Q78: =IF(AND(E78<>"",E78>Vencimentos!D70),F78*0.00033*(E78-Vencimentos!D70),0) -> 0
B79: 69 | C79: 2026 | D79: DEZ | F79: =Reajustes!H9 -> 2985.1865 | H79: =O78-IF(G79="",0,G79) -> 280440.88 | L79: =H79 -> 280440.88 | N79: =H79 -> 280440.88 | O79: =H79 -> 280440.88 | P79: =IF(AND(E79<>"",E79>Vencimentos!D71),F79*0.02,0) -> 0 | Q79: =IF(AND(E79<>"",E79>Vencimentos!D71),F79*0.00033*(E79-Vencimentos!D71),0) -> 0
B80: 70 | C80: 2027 | D80: JAN | F80: =Reajustes!H9 -> 2985.1865 | H80: =O79-IF(G80="",0,G80) -> 280440.88 | L80: =H80 -> 280440.88 | N80: =H80 -> 280440.88 | O80: =H80 -> 280440.88 | P80: =IF(AND(E80<>"",E80>Vencimentos!D72),F80*0.02,0) -> 0 | Q80: =IF(AND(E80<>"",E80>Vencimentos!D72),F80*0.00033*(E80-Vencimentos!D72),0) -> 0
B81: 71 | C81: 2027 | D81: FEV | F81: =Reajustes!H9 -> 2985.1865 | H81: =O80-IF(G81="",0,G81) -> 280440.88 | L81: =H81 -> 280440.88 | N81: =H81 -> 280440.88 | O81: =H81 -> 280440.88 | P81: =IF(AND(E81<>"",E81>Vencimentos!D73),F81*0.02,0) -> 0 | Q81: =IF(AND(E81<>"",E81>Vencimentos!D73),F81*0.00033*(E81-Vencimentos!D73),0) -> 0
B82: 72 | C82: 2027 | D82: MAR | F82: =Reajustes!H9 -> 2985.1865 | H82: =O81-IF(G82="",0,G82) -> 280440.88 | K82: =Reajustes!F9 -> 0 | L82: =IF(K82=0,H82,H82*(1+K82)) -> 280440.88 | M82: =Reajustes!E10 -> 0.10690623 | N82: =L82*(1+M82) -> 310421.75 | O82: =N82 -> 310421.75 | P82: =IF(AND(E82<>"",E82>Vencimentos!D74),F82*0.02,0) -> 0 | Q82: =IF(AND(E82<>"",E82>Vencimentos!D74),F82*0.00033*(E82-Vencimentos!D74),0) -> 0
B83: 73 | C83: 2027 | D83: ABR | F83: =Reajustes!H10 -> 2985.1865 | H83: =O82-IF(G83="",0,G83) -> 310421.75 | L83: =H83 -> 310421.75 | N83: =H83 -> 310421.75 | O83: =H83 -> 310421.75 | P83: =IF(AND(E83<>"",E83>Vencimentos!D75),F83*0.02,0) -> 0 | Q83: =IF(AND(E83<>"",E83>Vencimentos!D75),F83*0.00033*(E83-Vencimentos!D75),0) -> 0 | R83: =Reajustes!I26 -> 79408.531
B84: 74 | C84: 2027 | D84: MAI | F84: =Reajustes!H10 -> 2985.1865 | H84: =O83-IF(G84="",0,G84) -> 310421.75 | L84: =H84 -> 310421.75 | N84: =H84 -> 310421.75 | O84: =H84 -> 310421.75 | P84: =IF(AND(E84<>"",E84>Vencimentos!D76),F84*0.02,0) -> 0 | Q84: =IF(AND(E84<>"",E84>Vencimentos!D76),F84*0.00033*(E84-Vencimentos!D76),0) -> 0
B85: 75 | C85: 2027 | D85: JUN | F85: =Reajustes!H10 -> 2985.1865 | H85: =O84-IF(G85="",0,G85) -> 310421.75 | L85: =H85 -> 310421.75 | N85: =H85 -> 310421.75 | O85: =H85 -> 310421.75 | P85: =IF(AND(E85<>"",E85>Vencimentos!D77),F85*0.02,0) -> 0 | Q85: =IF(AND(E85<>"",E85>Vencimentos!D77),F85*0.00033*(E85-Vencimentos!D77),0) -> 0
B86: 76 | C86: 2027 | D86: JUL | F86: =Reajustes!H10 -> 2985.1865 | H86: =O85-IF(G86="",0,G86) -> 310421.75 | L86: =H86 -> 310421.75 | N86: =H86 -> 310421.75 | O86: =H86 -> 310421.75 | P86: =IF(AND(E86<>"",E86>Vencimentos!D78),F86*0.02,0) -> 0 | Q86: =IF(AND(E86<>"",E86>Vencimentos!D78),F86*0.00033*(E86-Vencimentos!D78),0) -> 0
B87: 77 | C87: 2027 | D87: AGO | F87: =Reajustes!H10 -> 2985.1865 | H87: =O86-IF(G87="",0,G87) -> 310421.75 | L87: =H87 -> 310421.75 | N87: =H87 -> 310421.75 | O87: =H87 -> 310421.75 | P87: =IF(AND(E87<>"",E87>Vencimentos!D79),F87*0.02,0) -> 0 | Q87: =IF(AND(E87<>"",E87>Vencimentos!D79),F87*0.00033*(E87-Vencimentos!D79),0) -> 0
B88: 78 | C88: 2027 | D88: SET | F88: =Reajustes!H10 -> 2985.1865 | H88: =O87-IF(G88="",0,G88) -> 310421.75 | L88: =H88 -> 310421.75 | N88: =H88 -> 310421.75 | O88: =H88 -> 310421.75 | P88: =IF(AND(E88<>"",E88>Vencimentos!D80),F88*0.02,0) -> 0 | Q88: =IF(AND(E88<>"",E88>Vencimentos!D80),F88*0.00033*(E88-Vencimentos!D80),0) -> 0
B89: 79 | C89: 2027 | D89: OUT | F89: =Reajustes!H10 -> 2985.1865 | H89: =O88-IF(G89="",0,G89) -> 310421.75 | L89: =H89 -> 310421.75 | N89: =H89 -> 310421.75 | O89: =H89 -> 310421.75 | P89: =IF(AND(E89<>"",E89>Vencimentos!D81),F89*0.02,0) -> 0 | Q89: =IF(AND(E89<>"",E89>Vencimentos!D81),F89*0.00033*(E89-Vencimentos!D81),0) -> 0
B90: 80 | C90: 2027 | D90: NOV | F90: =Reajustes!H10 -> 2985.1865 | H90: =O89-IF(G90="",0,G90) -> 310421.75 | L90: =H90 -> 310421.75 | N90: =H90 -> 310421.75 | O90: =H90 -> 310421.75 | P90: =IF(AND(E90<>"",E90>Vencimentos!D82),F90*0.02,0) -> 0 | Q90: =IF(AND(E90<>"",E90>Vencimentos!D82),F90*0.00033*(E90-Vencimentos!D82),0) -> 0
B91: 81 | C91: 2027 | D91: DEZ | F91: =Reajustes!H10 -> 2985.1865 | H91: =O90-IF(G91="",0,G91) -> 310421.75 | L91: =H91 -> 310421.75 | N91: =H91 -> 310421.75 | O91: =H91 -> 310421.75 | P91: =IF(AND(E91<>"",E91>Vencimentos!D83),F91*0.02,0) -> 0 | Q91: =IF(AND(E91<>"",E91>Vencimentos!D83),F91*0.00033*(E91-Vencimentos!D83),0) -> 0
B92: 82 | C92: 2028 | D92: JAN | F92: =Reajustes!H10 -> 2985.1865 | H92: =O91-IF(G92="",0,G92) -> 310421.75 | L92: =H92 -> 310421.75 | N92: =H92 -> 310421.75 | O92: =H92 -> 310421.75 | P92: =IF(AND(E92<>"",E92>Vencimentos!D84),F92*0.02,0) -> 0 | Q92: =IF(AND(E92<>"",E92>Vencimentos!D84),F92*0.00033*(E92-Vencimentos!D84),0) -> 0
B93: 83 | C93: 2028 | D93: FEV | F93: =Reajustes!H10 -> 2985.1865 | H93: =O92-IF(G93="",0,G93) -> 310421.75 | L93: =H93 -> 310421.75 | N93: =H93 -> 310421.75 | O93: =H93 -> 310421.75 | P93: =IF(AND(E93<>"",E93>Vencimentos!D85),F93*0.02,0) -> 0 | Q93: =IF(AND(E93<>"",E93>Vencimentos!D85),F93*0.00033*(E93-Vencimentos!D85),0) -> 0
B94: 84 | C94: 2028 | D94: MAR | F94: =Reajustes!H10 -> 2985.1865 | H94: =O93-IF(G94="",0,G94) -> 310421.75 | K94: =Reajustes!F10 -> 0 | L94: =IF(K94=0,H94,H94*(1+K94)) -> 310421.75 | M94: =Reajustes!E11 -> 0.10690623 | N94: =L94*(1+M94) -> 343607.77 | O94: =N94 -> 343607.77 | P94: =IF(AND(E94<>"",E94>Vencimentos!D86),F94*0.02,0) -> 0 | Q94: =IF(AND(E94<>"",E94>Vencimentos!D86),F94*0.00033*(E94-Vencimentos!D86),0) -> 0
B95: 85 | C95: 2028 | D95: ABR | F95: =Reajustes!H11 -> 2985.1865 | H95: =O94-IF(G95="",0,G95) -> 343607.77 | L95: =H95 -> 343607.77 | N95: =H95 -> 343607.77 | O95: =H95 -> 343607.77 | P95: =IF(AND(E95<>"",E95>Vencimentos!D87),F95*0.02,0) -> 0 | Q95: =IF(AND(E95<>"",E95>Vencimentos!D87),F95*0.00033*(E95-Vencimentos!D87),0) -> 0 | R95: =Reajustes!I27 -> 87897.797
B96: 86 | C96: 2028 | D96: MAI | F96: =Reajustes!H11 -> 2985.1865 | H96: =O95-IF(G96="",0,G96) -> 343607.77 | L96: =H96 -> 343607.77 | N96: =H96 -> 343607.77 | O96: =H96 -> 343607.77 | P96: =IF(AND(E96<>"",E96>Vencimentos!D88),F96*0.02,0) -> 0 | Q96: =IF(AND(E96<>"",E96>Vencimentos!D88),F96*0.00033*(E96-Vencimentos!D88),0) -> 0
B97: 87 | C97: 2028 | D97: JUN | F97: =Reajustes!H11 -> 2985.1865 | H97: =O96-IF(G97="",0,G97) -> 343607.77 | L97: =H97 -> 343607.77 | N97: =H97 -> 343607.77 | O97: =H97 -> 343607.77 | P97: =IF(AND(E97<>"",E97>Vencimentos!D89),F97*0.02,0) -> 0 | Q97: =IF(AND(E97<>"",E97>Vencimentos!D89),F97*0.00033*(E97-Vencimentos!D89),0) -> 0
B98: 88 | C98: 2028 | D98: JUL | F98: =Reajustes!H11 -> 2985.1865 | H98: =O97-IF(G98="",0,G98) -> 343607.77 | L98: =H98 -> 343607.77 | N98: =H98 -> 343607.77 | O98: =H98 -> 343607.77 | P98: =IF(AND(E98<>"",E98>Vencimentos!D90),F98*0.02,0) -> 0 | Q98: =IF(AND(E98<>"",E98>Vencimentos!D90),F98*0.00033*(E98-Vencimentos!D90),0) -> 0
B99: 89 | C99: 2028 | D99: AGO | F99: =Reajustes!H11 -> 2985.1865 | H99: =O98-IF(G99="",0,G99) -> 343607.77 | L99: =H99 -> 343607.77 | N99: =H99 -> 343607.77 | O99: =H99 -> 343607.77 | P99: =IF(AND(E99<>"",E99>Vencimentos!D91),F99*0.02,0) -> 0 | Q99: =IF(AND(E99<>"",E99>Vencimentos!D91),F99*0.00033*(E99-Vencimentos!D91),0) -> 0
B100: 90 | C100: 2028 | D100: SET | F100: =Reajustes!H11 -> 2985.1865 | H100: =O99-IF(G100="",0,G100) -> 343607.77 | L100: =H100 -> 343607.77 | N100: =H100 -> 343607.77 | O100: =H100 -> 343607.77 | P100: =IF(AND(E100<>"",E100>Vencimentos!D92),F100*0.02,0) -> 0 | Q100: =IF(AND(E100<>"",E100>Vencimentos!D92),F100*0.00033*(E100-Vencimentos!D92),0) -> 0
B101: 91 | C101: 2028 | D101: OUT | F101: =Reajustes!H11 -> 2985.1865 | H101: =O100-IF(G101="",0,G101) -> 343607.77 | L101: =H101 -> 343607.77 | N101: =H101 -> 343607.77 | O101: =H101 -> 343607.77 | P101: =IF(AND(E101<>"",E101>Vencimentos!D93),F101*0.02,0) -> 0 | Q101: =IF(AND(E101<>"",E101>Vencimentos!D93),F101*0.00033*(E101-Vencimentos!D93),0) -> 0
B102: 92 | C102: 2028 | D102: NOV | F102: =Reajustes!H11 -> 2985.1865 | H102: =O101-IF(G102="",0,G102) -> 343607.77 | L102: =H102 -> 343607.77 | N102: =H102 -> 343607.77 | O102: =H102 -> 343607.77 | P102: =IF(AND(E102<>"",E102>Vencimentos!D94),F102*0.02,0) -> 0 | Q102: =IF(AND(E102<>"",E102>Vencimentos!D94),F102*0.00033*(E102-Vencimentos!D94),0) -> 0
...

Sheet Índices IPCA
A1: SÉRIE HISTÓRICA IPCA - IBGE
A2: Fonte: IBGE | Atualizado até MAR/2026 | Início: MAR/2021 (mês do contrato)
A3: ANO | B3: MÊS | C3: NÚM. ÍNDICE | D3: VAR. MENSAL | E3: VAR. ACUM. DESDE MAR/21
A4: 2021 | B4: MAR | C4: 5674.72 | E4: 0
A5: 2021 | B5: ABR | C5: 5692.31 | D5: =(C5-C4)/C4 -> 0.0030997124 | E5: =C5/C$4-1 -> 0.0030997124
A6: 2021 | B6: MAI | C6: 5739.56 | D6: =(C6-C5)/C5 -> 0.0083006723 | E6: =C6/C$4-1 -> 0.011426114
A7: 2021 | B7: JUN | C7: 5769.98 | D7: =(C7-C6)/C6 -> 0.0053000578 | E7: =C7/C$4-1 -> 0.016786731
A8: 2021 | B8: JUL | C8: 5825.37 | D8: =(C8-C7)/C7 -> 0.0095996867 | E8: =C8/C$4-1 -> 0.026547565
A9: 2021 | B9: AGO | C9: 5876.05 | D9: =(C9-C8)/C8 -> 0.0086998766 | E9: =C9/C$4-1 -> 0.035478402
A10: 2021 | B10: SET | C10: 5944.21 | D10: =(C10-C9)/C9 -> 0.011599629 | E10: =C10/C$4-1 -> 0.047489568
A11: 2021 | B11: OUT | C11: 6018.51 | D11: =(C11-C10)/C10 -> 0.012499558 | E11: =C11/C$4-1 -> 0.060582725
A12: 2021 | B12: NOV | C12: 6075.69 | D12: =(C12-C11)/C11 -> 0.0095006904 | E12: =C12/C$4-1 -> 0.070658993
A13: 2021 | B13: DEZ | C13: 6120.04 | D13: =(C13-C12)/C12 -> 0.0072995824 | E13: =C13/C$4-1 -> 0.078474356
A14: 2022 | B14: JAN | C14: 6153.09 | D14: =(C14-C13)/C13 -> 0.0054002915 | E14: =C14/C$4-1 -> 0.084298432
A15: 2022 | B15: FEV | C15: 6215.24 | D15: =(C15-C14)/C14 -> 0.010100616 | E15: =C15/C$4-1 -> 0.095250515
A16: 2022 | B16: MAR | C16: 6315.93 | D16: =(C16-C15)/C15 -> 0.016200501 | E16: =C16/C$4-1 -> 0.11299412
... A64: 2026 | B64: MAR | C64: 7545.54 | D64: =(C64-C63)/C63 -> 0.0087997946 | E64: =C64/C$4-1 -> 0.32967618

Sheet Reajustes
A1: PARÂMETROS DE REAJUSTE ANUAL — PARCELAS MENSAIS
A2: Cláusula 2.2.1 — Correção: IPCA acumulado 12 meses + Juros compostos 0,85% a.m.
A3: ANO CONTRATUAL | B3: PARCELAS | C3: PERÍODO | D3: JUROS a.m. | E3: JUROS COMP. 12 MESES | F3: IPCA ACUM 12 MESES | G3: FATOR CORREÇÃO | H3: PARCELA MENSAL (R$)
A4: 1º ANO | B4: 1-12 | C4: ABR/21 a MAR/22 | D4: 0.0085 | E4: =(1+D4)^12-1 -> 0.10690623 | F4: ='Índices IPCA'!C16/'Índices IPCA'!C4-1 -> 0.11299412 | G4: 1 | H4: 1351.05
A5: 2º ANO | B5: 13-24 | C5: ABR/22 a MAR/23 | D5: 0.0085 | E5: =(1+D5)^12-1 -> 0.10690623 | F5: ='Índices IPCA'!C28/'Índices IPCA'!C16-1 -> 0.046507799 | G5: =IF(F4=0,1,(1+F4)*(1+E5)) -> 1.2319801 | H5: =H4*G5 -> 1664.4667
A6: 3º ANO | B6: 25-36 | C6: ABR/23 a MAR/24 | D6: 0.0085 | E6: =(1+D6)^12-1 -> 0.10690623 | F6: ='Índices IPCA'!C40/'Índices IPCA'!C28-1 -> 0.03925612 | G6: =IF(F5=0,1,(1+F5)*(1+E6)) -> 1.158386 | H6: =H5*G6 -> 1928.095
A7: 4º ANO | B7: 37-48 | C7: ABR/24 a MAR/25 | D7: 0.0085 | E7: =(1+D7)^12-1 -> 0.10690623 | F7: ='Índices IPCA'!C52/'Índices IPCA'!C40-1 -> 0.054772504 | G7: =IF(F6=0,1,(1+F6)*(1+E7)) -> 1.1503591 | H7: =H6*G7 -> 2218.0015
A8: 5º ANO | B8: 49-60 | C8: ABR/25 a MAR/26 | D8: 0.0085 | E8: =(1+D8)^12-1 -> 0.10690623 | F8: ='Índices IPCA'!C64/'Índices IPCA'!C52-1 -> 0.041427779 | G8: =IF(F7=0,1,(1+F7)*(1+E8)) -> 1.1675343 | H8: =H7*G8 -> 2589.5928
A9: 6º ANO | B9: 61-72 | C9: ABR/26 a MAR/27 | D9: 0.0085 | E9: =(1+D9)^12-1 -> 0.10690623 | F9: 0 | G9: =IF(F8=0,1,(1+F8)*(1+E9)) -> 1.1527629 | H9: =H8*G9 -> 2985.1865
A10: 7º ANO | B10: 73-84 | C10: ABR/27 a MAR/28 | D10: 0.0085 | E10: =(1+D10)^12-1 -> 0.10690623 | F10: 0 | G10: =IF(F9=0,1,(1+F9)*(1+E10)) -> 1 | H10: =H9*G10 -> 2985.1865
A11: 8º ANO | B11: 85-96 | C11: ABR/28 a MAR/29 | D11: 0.0085 | E11: =(1+D11)^12-1 -> 0.10690623 | F11: 0 | G11: =IF(F10=0,1,(1+F10)*(1+E11)) -> 1 | H11: =H10*G11 -> 2985.1865
A12: 9º ANO | B12: 97-108 | C12: ABR/29 a MAR/30 | D12: 0.0085 | E12: =(1+D12)^12-1 -> 0.10690623 | F12: 0 | G12: =IF(F11=0,1,(1+F11)*(1+E12)) -> 1 | H12: =H11*G12 -> 2985.1865
A13: 10º ANO | B13: 109-120 | C13: ABR/30 a MAR/31 | D13: 0.0085 | E13: =(1+D13)^12-1 -> 0.10690623 | F13: 0 | G13: =IF(F12=0,1,(1+F12)*(1+E13)) -> 1 | H13: =H12*G13 -> 2985.1865
A16: SALDO REMANESCENTE — PARCELAS ANUAIS (Cláusula 2.2.2)
A17: Dívida: R$ 50.000 | 10 parcelas anuais | 1º reajuste: ABR/2023 | Ordem: Pagamento → Reajuste
A18: Saldo Inicial (ABR/2022): | F18: 50000
A20: Nº | B20: ANIVERSÁRIO | C20: SALDO INICIAL | D20: PAGAMENTO | E20: APÓS PAGAMENTO | F20: IPCA ACUM 12 MESES | G20: JUROS COMP. 12 MESES | H20: REAJUSTE? | I20: SALDO REMANESCENTE
A21: 1 | B21: ABR/2022 | C21: =F18 -> 50000 | D21: 5000 | E21: =C21-D21 -> 45000 | H21: NÃO | I21: =E21 -> 45000
A22: 2 | B22: ABR/2023 | C22: =I21 -> 45000 | D22: 5000 | E22: =C22-D22 -> 40000 | F22: ='Índices IPCA'!C28/'Índices IPCA'!C16-1 -> 0.046507799 | G22: =(1+0.0085)^12-1 -> 0.10690623 | H22: SIM | I22: =IF(F22=0,E22*(1+G22),E22*(1+F22)*(1+G22)) -> 46335.44
A23: 3 | B23: ABR/2024 | C23: =I22 -> 46335.44 | D23: 0 | E23: =C23-D23 -> 46335.44 | F23: ='Índices IPCA'!C40/'Índices IPCA'!C28-1 -> 0.03925612 | G23: =(1+0.0085)^12-1 -> 0.10690623 | H23: SIM | I23: =IF(F23=0,E23*(1+G23),E23*(1+F23)*(1+G23)) -> 53302.394
A24: 4 | B24: ABR/2025 | C24: =I23 -> 53302.394 | D24: 0 | E24: =C24-D24 -> 53302.394 | F24: ='Índices IPCA'!C52/'Índices IPCA'!C40-1 -> 0.054772504 | G24: =(1+0.0085)^12-1 -> 0.10690623 | H24: SIM | I24: =IF(F24=0,E24*(1+G24),E24*(1+F24)*(1+G24)) -> 62232.37
A25: 5 | B25: ABR/2026 | C25: =I24 -> 62232.37 | D25: 0 | E25: =C25-D25 -> 62232.37 | F25: ='Índices IPCA'!C64/'Índices IPCA'!C52-1 -> 0.041427779 | G25: =(1+0.0085)^12-1 -> 0.10690623 | H25: SIM | I25: =IF(F25=0,E25*(1+G25),E25*(1+F25)*(1+G25)) -> 71739.167
A26: 6 | B26: ABR/2027 | C26: =I25 -> 71739.167 | D26: 0 | E26: =C26-D26 -> 71739.167 | F26: 0 | G26: =(1+0.0085)^12-1 -> 0.10690623 | H26: SIM | I26: =IF(F26=0,E26*(1+G26),E26*(1+F26)*(1+G26)) -> 79408.531
A27: 7 | B27: ABR/2028 | C27: =I26 -> 79408.531 | D27: 0 | E27: =C27-D27 -> 79408.531 | F27: 0 | G27: =(1+0.0085)^12-1 -> 0.10690623 | H27: SIM | I27: =IF(F27=0,E27*(1+G27),E27*(1+F27)*(1+G27)) -> 87897.797
A28: 8 | B28: ABR/2029 | C28: =I27 -> 87897.797 | D28: 0 | E28: =C28-D28 -> 87897.797 | F28: 0 | G28: =(1+0.0085)^12-1 -> 0.10690623 | H28: SIM | I28: =IF(F28=0,E28*(1+G28),E28*(1+F28)*(1+G28)) -> 97294.619
A29: 9 | B29: ABR/2030 | C29: =I28 -> 97294.619 | D29: 0 | E29: =C29-D29 -> 97294.619 | F29: 0 | G29: =(1+0.0085)^12-1 -> 0.10690623 | H29: SIM | I29: =IF(F29=0,E29*(1+G29),E29*(1+F29)*(1+G29)) -> 107696.02
A30: 10 | B30: ABR/2031 | C30: =I29 -> 107696.02 | D30: 0 | E30: =C30-D30 -> 107696.02 | F30: 0 | G30: =(1+0.0085)^12-1 -> 0.10690623 | H30: SIM | I30: =IF(F30=0,E30*(1+G30),E30*(1+F30)*(1+G30)) -> 119209.4
A31: TOTAIS | D31: =SUM(D21:D30) -> 10000
A33: SALDO REMANESCENTE ATUALIZADO: | I33: =I30 -> 119209.4
A34: Total pago (parcelas anuais): | I34: =D31 -> 10000
A36: NOTAS:
A37: ABR/2022: 1ª parcela devida, SEM reajuste — saldo = R$ 50.000 - R$ 5.000 = R$ 45.000
A38: ABR/2023: 1º REAJUSTE — primeiro paga, depois corrige o saldo pelo IPCA + juros
A39: Parcela 1 paga em DEZ/2021 | Parcela 2 paga em DEZ/2022 | Parcelas 3-10 não pagas
A40: Parcelas 6-10: sem IPCA divulgado — correção apenas por juros compostos 0,85% a.m.

Sheet Vencimentos
A1: VENCIMENTOS AJUSTADOS — DIAS ÚTEIS E FERIADOS
A2: PARCELA | B2: MÊS/ANO | C2: VENC. ORIGINAL | D2: VENC. ÚTIL | E2: FERIADO/ FIM SEMANA? | F2: OBSERVAÇÃO
A3: 1 | B3: ABR/2021 | C3: 44296 | D3: 44298 | E3: SIM | F3: Sábado
A4: 2 | B4: MAI/2021 | C4: 44326 | D4: 44326
A5: 3 | B5: JUN/2021 | C5: 44357 | D5: 44357
A6: 4 | B6: JUL/2021 | C6: 44387 | D6: 44389 | E6: SIM | F6: Sábado
A7: 5 | B7: AGO/2021 | C7: 44418 | D7: 44418
A8: 6 | B8: SET/2021 | C8: 44449 | D8: 44449
A9: 7 | B9: OUT/2021 | C9: 44479 | D9: 44480 | E9: SIM | F9: Domingo
A10: 8 | B10: NOV/2021 | C10: 44510 | D10: 44510
A11: 9 | B11: DEZ/2021 | C11: 44540 | D11: 44540
A12: 10 | B12: JAN/2022 | C12: 44571 | D12: 44571
A13: 11 | B13: FEV/2022 | C13: 44602 | D13: 44602
A14: 12 | B14: MAR/2022 | C14: 44630 | D14: 44630
A15: 13 | B15: ABR/2022 | C15: 44661 | D15: 44662 | E15: SIM | F15: Domingo
A16: 14 | B16: MAI/2022 | C16: 44691 | D16: 44691
A17: 15 | B17: JUN/2022 | C17: 44722 | D17: 44722
A18: 16 | B18: JUL/2022 | C18: 44752 | D18: 44753 | E18: SIM | F18: Domingo
A19: 17 | B19: AGO/2022 | C19: 44783 | D19: 44783
A20: 18 | B20: SET/2022 | C20: 44814 | D20: 44816 | E20: SIM | F20: Sábado
A21: 19 | B21: OUT/2022 | C21: 44844 | D21: 44844
A22: 20 | B22: NOV/2022 | C22: 44875 | D22: 44875
A23: 21 | B23: DEZ/2022 | C23: 44905 | D23: 44907 | E23: SIM | F23: Sábado
A24: 22 | B24: JAN/2023 | C24: 44936 | D24: 44936
A25: 23 | B25: FEV/2023 | C25: 44967 | D25: 44967
A26: 24 | B26: MAR/2023 | C26: 44995 | D26: 44995
A27: 25 | B27: ABR/2023 | C27: 45026 | D27: 45026
A28: 26 | B28: MAI/2023 | C28: 45056 | D28: 45056
A29: 27 | B29: JUN/2023 | C29: 45087 | D29: 45089 | E29: SIM | F29: Sábado
A30: 28 | B30: JUL/2023 | C30: 45117 | D30: 45117
A31: 29 | B31: AGO/2023 | C31: 45148 | D31: 45148
A32: 30 | B32: SET/2023 | C32: 45179 | D32: 45180 | E32: SIM | F32: Domingo
A33: 31 | B33: OUT/2023 | C33: 45209 | D33: 45209
A34: 32 | B34: NOV/2023 | C34: 45240 | D34: 45240
A35: 33 | B35: DEZ/2023 | C35: 45270 | D35: 45271 | E35: SIM | F35: Domingo
A36: 34 | B36: JAN/2024 | C36: 45301 | D36: 45301
A37: 35 | B37: FEV/2024 | C37: 45332 | D37: 45334 | E37: SIM | F37: Sábado
A38: 36 | B38: MAR/2024 | C38: 45361 | D38: 45362 | E38: SIM | F38: Domingo
A39: 37 | B39: ABR/2024 | C39: 45392 | D39: 45392
A40: 38 | B40: MAI/2024 | C40: 45422 | D40: 45422
A41: 39 | B41: JUN/2024 | C41: 45453 | D41: 45453
A42: 40 | B42: JUL/2024 | C42: 45483 | D42: 45483
A43: 41 | B43: AGO/2024 | C43: 45514 | D43: 45516 | E43: SIM | F43: Sábado
A44: 42 | B44: SET/2024 | C44: 45545 | D44: 45545
A45: 43 | B45: OUT/2024 | C45: 45575 | D45: 45575
A46: 44 | B46: NOV/2024 | C46: 45606 | D46: 45607 | E46: SIM | F46: Domingo
A47: 45 | B47: DEZ/2024 | C47: 45636 | D47: 45636
A48: 46 | B48: JAN/2025 | C48: 45667 | D48: 45667
A49: 47 | B49: FEV/2025 | C49: 45698 | D49: 45698
A50: 48 | B50: MAR/2025 | C50: 45726 | D50: 45726
A51: 49 | B51: ABR/2025 | C51: 45757 | D51: 45757
A52: 50 | B52: MAI/2025 | C52: 45787 | D52: 45789 | E52: SIM | F52: Sábado
A53: 51 | B53: JUN/2025 | C53: 45818 | D53: 45818
A54: 52 | B54: JUL/2025 | C54: 45848 | D54: 45848
A55: 53 | B55: AGO/2025 | C55: 45879 | D55: 45880 | E55: SIM | F55: Domingo
A56: 54 | B56: SET/2025 | C56: 45910 | D56: 45910
A57: 55 | B57: OUT/2025 | C57: 45940 | D57: 45940
A58: 56 | B58: NOV/2025 | C58: 45971 | D58: 45971
A59: 57 | B59: DEZ/2025 | C59: 46001 | D59: 46001
A60: 58 | B60: JAN/2026 | C60: 46032 | D60: 46034 | E60: SIM | F60: Sábado
A61: 59 | B61: FEV/2026 | C61: 46063 | D61: 46063
A62: 60 | B62: MAR/2026 | C62: 46091 | D62: 46091
A63: 61 | B63: ABR/2026 | C63: 46122 | D63: 46122
A64: 62 | B64: MAI/2026 | C64: 46152 | D64: 46153 | E64: SIM | F64: Domingo
A65: 63 | B65: JUN/2026 | C65: 46183 | D65: 46183
A66: 64 | B66: JUL/2026 | C66: 46213 | D66: 46213
A67: 65 | B67: AGO/2026 | C67: 46244 | D67: 46244
A68: 66 | B68: SET/2026 | C68: 46275 | D68: 46275
A69: 67 | B69: OUT/2026 | C69: 46305 | D69: 46308 | E69: SIM | F69: Sábado
A70: 68 | B70: NOV/2026 | C70: 46336 | D70: 46336
A71: 69 | B71: DEZ/2026 | C71: 46366 | D71: 46366
A72: 70 | B72: JAN/2027 | C72: 46397 | D72: 46398 | E72: SIM | F72: Domingo
A73: 71 | B73: FEV/2027 | C73: 46428 | D73: 46429 | E73: SIM | F73: Carnaval Ter
A74: 72 | B74: MAR/2027 | C74: 46456 | D74: 46456
A75: 73 | B75: ABR/2027 | C75: 46487 | D75: 46489 | E75: SIM | F75: Sábado
A76: 74 | B76: MAI/2027 | C76: 46517 | D76: 46517
A77: 75 | B77: JUN/2027 | C77: 46548 | D77: 46548
A78: 76 | B78: JUL/2027 | C78: 46578 | D78: 46580 | E78: SIM | F78: Sábado
A79: 77 | B79: AGO/2027 | C79: 46609 | D79: 46609
A80: 78 | B80: SET/2027 | C80: 46640 | D80: 46640
A81: 79 | B81: OUT/2027 | C81: 46670 | D81: 46671 | E81: SIM | F81: Domingo
A82: 80 | B82: NOV/2027 | C82: 46701 | D82: 46701
A83: 81 | B83: DEZ/2027 | C83: 46731 | D83: 46731
A84: 82 | B84: JAN/2028 | C84: 46762 | D84: 46762
A85: 83 | B85: FEV/2028 | C85: 46793 | D85: 46793
A86: 84 | B86: MAR/2028 | C86: 46822 | D86: 46822
A87: 85 | B87: ABR/2028 | C87: 46853 | D87: 46853
A88: 86 | B88: MAI/2028 | C88: 46883 | D88: 46883
A89: 87 | B89: JUN/2028 | C89: 46914 | D89: 46916 | E89: SIM | F89: Sábado
A90: 88 | B90: JUL/2028 | C90: 46944 | D90: 46944
A91: 89 | B91: AGO/2028 | C91: 46975 | D91: 46975
A92: 90 | B92: SET/2028 | C92: 47006 | D92: 47007 | E92: SIM | F92: Domingo
A93: 91 | B93: OUT/2028 | C93: 47036 | D93: 47036
A94: 92 | B94: NOV/2028 | C94: 47067 | D94: 47067
A95: 93 | B95: DEZ/2028 | C95: 47097 | D95: 47098 | E95: SIM | F95: Domingo
A96: 94 | B96: JAN/2029 | C96: 47128 | D96: 47128
A97: 95 | B97: FEV/2029 | C97: 47159 | D97: 47161 | E97: SIM | F97: Sábado
A98: 96 | B98: MAR/2029 | C98: 47187 | D98: 47189 | E98: SIM | F98: Sábado
A99: 97 | B99: ABR/2029 | C99: 47218 | D99: 47218
A100: 98 | B100: MAI/2029 | C100: 47248 | D100: 47248
...

Sheet Saldo Devedor Atualizado
A1: ATUALIZAÇÃO DO SALDO DEVEDOR — METODOLOGIA CÁLCULO EXATO
A2: Saldo corrigido anualmente: Saldo → (-) Pagamentos do Período → IPCA acum 12M → Juros comp. 0,85% a.m.
A4: PARCELAS MENSAIS (Cláusula 2.2.1) — Saldo Inicial: R$ 162.126,24
A6: ANO CONTRATUAL | B6: PERÍODO | C6: SALDO INICIAL | D6: PGTOS NO PERÍODO | E6: SALDO APÓS PAGAMENTOS | F6: IPCA ACUM 12 MESES (%) | G6: FATOR IPCA | H6: JUROS COMP. 12M (%) | I6: SALDO DEV. ATUALIZADO
A7: 1º ANO | B7: ABR/21-MAR/22 | C7: 162126.24 | D7: =SUM('Parcelas Mensais'!G11:G22) -> 16712.64 | E7: =C7-D7 -> 145413.6 | F7: 0.112993 | G7: =1+F7 -> 1.112993 | H7: =(1+0.0085)^12-1 -> 0.10690623 | I7: 179146.47
A8: 2º ANO | B8: ABR/22-MAR/23 | C8: =I7 -> 179146.47 | D8: =SUM('Parcelas Mensais'!G23:G34) -> 17600.09 | E8: =C8-D8 -> 161546.38 | F8: 0.046507 | G8: =1+F8 -> 1.046507 | H8: =(1+0.0085)^12-1 -> 0.10690623 | I8: 187132.87
A9: 3º ANO | B9: ABR/23-MAR/24 | C9: =I8 -> 187132.87 | D9: =SUM('Parcelas Mensais'!G35:G46) -> 6000 | E9: =C9-D9 -> 181132.87 | F9: 0.039256 | G9: =1+F9 -> 1.039256 | H9: =(1+0.0085)^12-1 -> 0.10690623 | I9: 208367.76
A10: 4º ANO | B10: ABR/24-MAR/25 | C10: =I9 -> 208367.76 | D10: =SUM('Parcelas Mensais'!G47:G58) -> 0 | E10: =C10-D10 -> 208367.76 | F10: 0.054772 | G10: =1+F10 -> 1.054772 | H10: =(1+0.0085)^12-1 -> 0.10690623 | I10: 243276.3
A11: 5º ANO | B11: ABR/25-MAR/26 | C11: =I10 -> 243276.3 | D11: =SUM('Parcelas Mensais'!G59:G70) -> 0 | E11: =C11-D11 -> 243276.3 | F11: 0.041428 | G11: =1+F11 -> 1.041428 | H11: =(1+0.0085)^12-1 -> 0.10690623 | I11: 280440.01
A12: 6º ANO | B12: ABR/26-MAR/27 | C12: =I11 -> 280440.01 | D12: =SUM('Parcelas Mensais'!G71:G82) -> 0 | E12: =C12-D12 -> 280440.01 | F12: 0 | G12: =1+F12 -> 1 | H12: =(1+0.0085)^12-1 -> 0.10690623 | I12: =ROUND(E12*G12,2)+ROUND(ROUND(E12*G12,2)*10.6906/100,2) -> 310420.73
A13: 7º ANO | B13: ABR/27-MAR/28 | C13: =I12 -> 310420.73 | D13: =SUM('Parcelas Mensais'!G83:G94) -> 0 | E13: =C13-D13 -> 310420.73 | F13: 0 | G13: =1+F13 -> 1 | H13: =(1+0.0085)^12-1 -> 0.10690623 | I13: =ROUND(E13*G13,2)+ROUND(ROUND(E13*G13,2)*10.6906/100,2) -> 343606.57
A14: 8º ANO | B14: ABR/28-MAR/29 | C14: =I13 -> 343606.57 | D14: =SUM('Parcelas Mensais'!G95:G106) -> 0 | E14: =C14-D14 -> 343606.57 | F14: 0 | G14: =1+F14 -> 1 | H14: =(1+0.0085)^12-1 -> 0.10690623 | I14: =ROUND(E14*G14,2)+ROUND(ROUND(E14*G14,2)*10.6906/100,2) -> 380340.17
A15: 9º ANO | B15: ABR/29-MAR/30 | C15: =I14 -> 380340.17 | D15: =SUM('Parcelas Mensais'!G107:G118) -> 0 | E15: =C15-D15 -> 380340.17 | F15: 0 | G15: =1+F15 -> 1 | H15: =(1+0.0085)^12-1 -> 0.10690623 | I15: =ROUND(E15*G15,2)+ROUND(ROUND(E15*G15,2)*10.6906/100,2) -> 421000.82
A16: 10º ANO | B16: ABR/30-MAR/31 | C16: =I15 -> 421000.82 | D16: =SUM('Parcelas Mensais'!G119:G130) -> 0 | E16: =C16-D16 -> 421000.82 | F16: 0 | G16: =1+F16 -> 1 | H16: =(1+0.0085)^12-1 -> 0.10690623 | I16: =ROUND(E16*G16,2)+ROUND(ROUND(E16*G16,2)*10.6906/100,2) -> 466008.33
A17: TOTAL PGTOS: | D17: =SUM(D7:D16) -> 40312.73 | H17: SALDO FINAL: | I17: =I16 -> 466008.33
A20: PARCELAS ANUAIS (Cláusula 2.2.2) — Saldo Inicial: R$ 50.000,00 | 1º reajuste ABR/2023
A22: Nº | B22: ANIVERSÁRIO | C22: SALDO INICIAL | D22: PAGAMENTO | E22: APÓS PAGAMENTO | F22: IPCA ACUM 12M (%) | G22: FATOR IPCA | H22: JUROS COMP. 12M (%) | I22: SALDO REMANESCENTE
A23: 1 | B23: ABR/2022 | C23: 50000 | D23: 5000 | E23: =C23-D23 -> 45000 | G23: 1 | I23: =E23 -> 45000
A24: 2 | B24: ABR/2023 | C24: =I23 -> 45000 | D24: 5000 | E24: =C24-D24 -> 40000 | F24: ='Índices IPCA'!C28/'Índices IPCA'!C16-1 -> 0.046507799 | G24: =1+F24 -> 1.0465078 | H24: =(1+0.0085)^12-1 -> 0.10690623 | I24: =IF(F24=0,E24*(1+H24),E24*G24*(1+H24)) -> 46335.44
A25: 3 | B25: ABR/2024 | C25: =I24 -> 46335.44 | D25: 0 | E25: =C25-D25 -> 46335.44 | F25: ='Índices IPCA'!C40/'Índices IPCA'!C28-1 -> 0.03925612 | G25: =1+F25 -> 1.0392561 | H25: =(1+0.0085)^12-1 -> 0.10690623 | I25: =IF(F25=0,E25*(1+H25),E25*G25*(1+H25)) -> 53302.394
A26: 4 | B26: ABR/2025 | C26: =I25 -> 53302.394 | D26: 0 | E26: =C26-D26 -> 53302.394 | F26: ='Índices IPCA'!C52/'Índices IPCA'!C40-1 -> 0.054772504 | G26: =1+F26 -> 1.0547725 | H26: =(1+0.0085)^12-1 -> 0.10690623 | I26: =IF(F26=0,E26*(1+H26),E26*G26*(1+H26)) -> 62232.37
A27: 5 | B27: ABR/2026 | C27: =I26 -> 62232.37 | D27: 0 | E27: =C27-D27 -> 62232.37 | F27: ='Índices IPCA'!C64/'Índices IPCA'!C52-1 -> 0.041427779 | G27: =1+F27 -> 1.0414278 | H27: =(1+0.0085)^12-1 -> 0.10690623 | I27: =IF(F27=0,E27*(1+H27),E27*G27*(1+H27)) -> 71739.167
A28: 6 | B28: ABR/2027 | C28: =I27 -> 71739.167 | D28: 0 | E28: =C28-D28 -> 71739.167 | F28: 0 | G28: =1+F28 -> 1 | H28: =(1+0.0085)^12-1 -> 0.10690623 | I28: =IF(F28=0,E28*(1+H28),E28*G28*(1+H28)) -> 79408.531
A29: 7 | B29: ABR/2028 | C29: =I28 -> 79408.531 | D29: 0 | E29: =C29-D29 -> 79408.531 | F29: 0 | G29: =1+F29 -> 1 | H29: =(1+0.0085)^12-1 -> 0.10690623 | I29: =IF(F29=0,E29*(1+H29),E29*G29*(1+H29)) -> 87897.797
A30: 8 | B30: ABR/2029 | C30: =I29 -> 87897.797 | D30: 0 | E30: =C30-D30 -> 87897.797 | F30: 0 | G30: =1+F30 -> 1 | H30: =(1+0.0085)^12-1 -> 0.10690623 | I30: =IF(F30=0,E30*(1+H30),E30*G30*(1+H30)) -> 97294.619
A31: 9 | B31: ABR/2030 | C31: =I30 -> 97294.619 | D31: 0 | E31: =C31-D31 -> 97294.619 | F31: 0 | G31: =1+F31 -> 1 | H31: =(1+0.0085)^12-1 -> 0.10690623 | I31: =IF(F31=0,E31*(1+H31),E31*G31*(1+H31)) -> 107696.02
A32: 10 | B32: ABR/2031 | C32: =I31 -> 107696.02 | D32: 0 | E32: =C32-D32 -> 107696.02 | F32: 0 | G32: =1+F32 -> 1 | H32: =(1+0.0085)^12-1 -> 0.10690623 | I32: =IF(F32=0,E32*(1+H32),E32*G32*(1+H32)) -> 119209.4
A33: TOTAL PGTOS: | D33: =SUM(D23:D32) -> 10000 | H33: SALDO FINAL: | I33: =I32 -> 119209.4
A35: DÍVIDA TOTAL ATUALIZADA
A36: Saldo Devedor Mensal: | I36: =I17 -> 466008.33
A37: Saldo Devedor Anual: | I37: =I33 -> 119209.4
A38: TOTAL DÍVIDA ATUALIZADA: | I38: =I36+I37 -> 585217.73
A39: Total pago (mensal + anual): | I39: =D17+D33 -> 50312.73
A41: METODOLOGIA (idêntica ao Cálculo Exato - calculoexato.com.br):
A42: 1. Toma o saldo devedor do período anterior
A43: 2. Subtrai os pagamentos EFETIVOS realizados no período (12 parcelas por ano contratual)
A44: 3. Aplica IPCA acumulado 12 meses (ABR a ABR)
A45: 4. Aplica juros compostos 0,85% a.m. (= 10,69060% em 12 meses)
A46: 5. Resultado = novo saldo devedor atualizado
A48: Os pagamentos são automaticamente puxados da aba "Parcelas Mensais" coluna G (Vlr Pago).
A49: Para as anuais: ordem Pagamento → Reajuste, com 1º reajuste em ABR/2023.

Sheet Mensais - Calc Exato
B1: CONTROLE — PARCELAS MENSAIS (Cálculo Exato)
B2: Saldo devedor: Saldo → (-) Pgto → Correção (IPCA+Juros separados, c/ arred. intermediário = método calculoexato.com.br)
B3: DADOS DO CONTRATO
B4: Compradora: | C4: UANDA SILVA CARVALHO | J4: CPF: | K4: 066.128.216-39
B5: Imóvel: | C5: Lote 16, Quadra D — Res. Parque das Nogueiras | J5: Data Contrato: | K5: 44279
B6: Saldo Mensal: | C6: 162126.24 | E6: Juros: | F6: 0,85% a.m. = 10,69060% em 12m | J6: Índice: | K6: IPCA (ABR a ABR)
B8: IDENTIFICAÇÃO | F8: VALORES (R$) | I8: IPCA | K8: CORREÇÃO ANUAL | P8: ENCARGOS ATRASO | R8: CLÁUS. 2.2.2
B9: Nº | C9: ANO | D9: MÊS | E9: DATA PGTO | F9: VLR A PAGAR (Saldo÷Rest) | G9: VLR PAGO | H9: SALDO BASE | I9: NÚM. ÍNDICE | J9: VAR. MENSAL | K9: IPCA ACUM 12M (%) | L9: VALOR ATUAL. IPCA (VA) | M9: JUROS COMP. 10,69060% | N9: SALDO DEV. VA + VJ | O9: SALDO DEVEDOR | P9: MULTA 2% | Q9: JUROS MORA 0,033%/dia | R9: SALDO REM. ANUAL | S9: ANUAL PAGO
B10: ENT. | C10: 2021 | D10: MAR | E10: 44279 | F10: 23569.58 | G10: 23569.58 | H10: 162126.24 | O10: =H10 -> 162126.24
B11: 1 | C11: 2021 | D11: ABR | E11: ='Parcelas Mensais'!E11 -> 44298 | F11: =H11/120 -> 1351.052 | G11: ='Parcelas Mensais'!G11 -> 1392.72 | H11: =O10 -> 162126.24 | I11: ='Parcelas Mensais'!I11 -> 5692.31 | J11: ='Parcelas Mensais'!J11 -> 0.0030997124 | L11: =O11 -> 160733.52 | N11: =O11 -> 160733.52 | O11: =H11-IF(G11="",0,G11) -> 160733.52 | P11: ='Parcelas Mensais'!P11 -> 0 | Q11: ='Parcelas Mensais'!Q11 -> 0
B12: 2 | C12: 2021 | D12: MAI | E12: ='Parcelas Mensais'!E12 -> 44323 | F12: =H12/119 -> 1350.7018 | G12: ='Parcelas Mensais'!G12 -> 1392.72 | H12: =O11 -> 160733.52 | I12: ='Parcelas Mensais'!I12 -> 5739.56 | J12: ='Parcelas Mensais'!J12 -> 0.0083006723 | L12: =O12 -> 159340.8 | N12: =O12 -> 159340.8 | O12: =H12-IF(G12="",0,G12) -> 159340.8 | P12: ='Parcelas Mensais'!P12 -> 0 | Q12: ='Parcelas Mensais'!Q12 -> 0
B13: 3 | C13: 2021 | D13: JUN | E13: ='Parcelas Mensais'!E13 -> 44357 | F13: =H13/118 -> 1350.3458 | G13: ='Parcelas Mensais'!G13 -> 1392.72 | H13: =O12 -> 159340.8 | I13: ='Parcelas Mensais'!I13 -> 5769.98 | J13: ='Parcelas Mensais'!J13 -> 0.0053000578 | L13: =O13 -> 157948.08 | N13: =O13 -> 157948.08 | O13: =H13-IF(G13="",0,G13) -> 157948.08 | P13: ='Parcelas Mensais'!P13 -> 0 | Q13: ='Parcelas Mensais'!Q13 -> 0
B14: 4 | C14: 2021 | D14: JUL | E14: ='Parcelas Mensais'!E14 -> 44386 | F14: =H14/117 -> 1349.9836 | G14: ='Parcelas Mensais'!G14 -> 1392.72 | H14: =O13 -> 157948.08 | I14: ='Parcelas Mensais'!I14 -> 5825.37 | J14: ='Parcelas Mensais'!J14 -> 0.0095996867 | L14: =O14 -> 156555.36 | N14: =O14 -> 156555.36 | O14: =H14-IF(G14="",0,G14) -> 156555.36 | P14: ='Parcelas Mensais'!P14 -> 0 | Q14: ='Parcelas Mensais'!Q14 -> 0
B15: 5 | C15: 2021 | D15: AGO | E15: ='Parcelas Mensais'!E15 -> 44413 | F15: =H15/116 -> 1349.6152 | G15: ='Parcelas Mensais'!G15 -> 1392.72 | H15: =O14 -> 156555.36 | I15: ='Parcelas Mensais'!I15 -> 5876.05 | J15: ='Parcelas Mensais'!J15 -> 0.0086998766 | L15: =O15 -> 155162.64 | N15: =O15 -> 155162.64 | O15: =H15-IF(G15="",0,G15) -> 155162.64 | P15: ='Parcelas Mensais'!P15 -> 0 | Q15: ='Parcelas Mensais'!Q15 -> 0
B16: 6 | C16: 2021 | D16: SET | E16: ='Parcelas Mensais'!E16 -> 44449 | F16: =H16/115 -> 1349.2403 | G16: ='Parcelas Mensais'!G16 -> 1392.72 | H16: =O15 -> 155162.64 | I16: ='Parcelas Mensais'!I16 -> 5944.21 | J16: ='Parcelas Mensais'!J16 -> 0.011599629 | L16: =O16 -> 153769.92 | N16: =O16 -> 153769.92 | O16: =H16-IF(G16="",0,G16) -> 153769.92 | P16: ='Parcelas Mensais'!P16 -> 0 | Q16: ='Parcelas Mensais'!Q16 -> 0
B17: 7 | C17: 2021 | D17: OUT | E17: ='Parcelas Mensais'!E17 -> 44480 | F17: =H17/114 -> 1348.8589 | G17: ='Parcelas Mensais'!G17 -> 1392.72 | H17: =O16 -> 153769.92 | I17: ='Parcelas Mensais'!I17 -> 6018.51 | J17: ='Parcelas Mensais'!J17 -> 0.012499558 | L17: =O17 -> 152377.2 | N17: =O17 -> 152377.2 | O17: =H17-IF(G17="",0,G17) -> 152377.2 | P17: ='Parcelas Mensais'!P17 -> 0 | Q17: ='Parcelas Mensais'!Q17 -> 0
B18: 8 | C18: 2021 | D18: NOV | E18: ='Parcelas Mensais'!E18 -> 44510 | F18: =H18/113 -> 1348.4708 | G18: ='Parcelas Mensais'!G18 -> 1392.72 | H18: =O17 -> 152377.2 | I18: ='Parcelas Mensais'!I18 -> 6075.69 | J18: ='Parcelas Mensais'!J18 -> 0.0095006904 | L18: =O18 -> 150984.48 | N18: =O18 -> 150984.48 | O18: =H18-IF(G18="",0,G18) -> 150984.48 | P18: ='Parcelas Mensais'!P18 -> 0 | Q18: ='Parcelas Mensais'!Q18 -> 0
B19: 9 | C19: 2021 | D19: DEZ | E19: ='Parcelas Mensais'!E19 -> 44540 | F19: =H19/112 -> 1348.0757 | G19: ='Parcelas Mensais'!G19 -> 1392.72 | H19: =O18 -> 150984.48 | I19: ='Parcelas Mensais'!I19 -> 6120.04 | J19: ='Parcelas Mensais'!J19 -> 0.0072995824 | L19: =O19 -> 149591.76 | N19: =O19 -> 149591.76 | O19: =H19-IF(G19="",0,G19) -> 149591.76 | P19: ='Parcelas Mensais'!P19 -> 0 | Q19: ='Parcelas Mensais'!Q19 -> 0 | S19: ='Parcelas Mensais'!S19 -> 5000
B20: 10 | C20: 2022 | D20: JAN | E20: ='Parcelas Mensais'!E20 -> 44572 | F20: =H20/111 -> 1347.6735 | G20: ='Parcelas Mensais'!G20 -> 1392.72 | H20: =O19 -> 149591.76 | I20: ='Parcelas Mensais'!I20 -> 6153.09 | J20: ='Parcelas Mensais'!J20 -> 0.0054002915 | L20: =O20 -> 148199.04 | N20: =O20 -> 148199.04 | O20: =H20-IF(G20="",0,G20) -> 148199.04 | P20: ='Parcelas Mensais'!P20 -> 27.021 | Q20: ='Parcelas Mensais'!Q20 -> 0.4458465
B21: 11 | C21: 2022 | D21: FEV | E21: ='Parcelas Mensais'!E21 -> 44602 | F21: =H21/110 -> 1347.264 | G21: ='Parcelas Mensais'!G21 -> 1392.72 | H21: =O20 -> 148199.04 | I21: ='Parcelas Mensais'!I21 -> 6215.24 | J21: ='Parcelas Mensais'!J21 -> 0.010100616 | L21: =O21 -> 146806.32 | N21: =O21 -> 146806.32 | O21: =H21-IF(G21="",0,G21) -> 146806.32 | P21: ='Parcelas Mensais'!P21 -> 0 | Q21: ='Parcelas Mensais'!Q21 -> 0
B22: 12 | C22: 2022 | D22: MAR | E22: ='Parcelas Mensais'!E22 -> 44630 | F22: =H22/109 -> 1346.847 | G22: ='Parcelas Mensais'!G22 -> 1392.72 | H22: =O21 -> 146806.32 | I22: ='Parcelas Mensais'!I22 -> 6315.93 | J22: ='Parcelas Mensais'!J22 -> 0.016200501 | K22: 0.112993 | L22: 161844.34 | M22: 17302.13 | N22: =L22+M22 -> 179146.47 | O22: =H22-IF(G22="",0,G22) -> 145413.6 | P22: ='Parcelas Mensais'!P22 -> 0 | Q22: ='Parcelas Mensais'!Q22 -> 0
B23: 13 | C23: 2022 | D23: ABR | E23: ='Parcelas Mensais'!E23 -> 44662 | F23: =H23/108 -> 1658.7636 | G23: ='Parcelas Mensais'!G23 -> 1392.72 | H23: =N22 -> 179146.47 | I23: ='Parcelas Mensais'!I23 -> 6382.88 | J23: ='Parcelas Mensais'!J23 -> 0.010600181 | L23: =O23 -> 177753.75 | N23: =O23 -> 177753.75 | O23: =H23-IF(G23="",0,G23) -> 177753.75 | P23: ='Parcelas Mensais'!P23 -> 0 | Q23: ='Parcelas Mensais'!Q23 -> 0 | R23: =Reajustes!I21 -> 45000
B24: 14 | C24: 2022 | D24: MAI | E24: ='Parcelas Mensais'!E24 -> 44691 | F24: =H24/107 -> 1661.25 | G24: ='Parcelas Mensais'!G24 -> 1392.72 | H24: =O23 -> 177753.75 | I24: ='Parcelas Mensais'!I24 -> 6412.88 | J24: ='Parcelas Mensais'!J24 -> 0.0047000727 | L24: =O24 -> 176361.03 | N24: =O24 -> 176361.03 | O24: =H24-IF(G24="",0,G24) -> 176361.03 | P24: ='Parcelas Mensais'!P24 -> 0 | Q24: ='Parcelas Mensais'!Q24 -> 0
B25: 15 | C25: 2022 | D25: JUN | E25: ='Parcelas Mensais'!E25 -> 44726 | F25: =H25/106 -> 1663.7833 | G25: ='Parcelas Mensais'!G25 -> 1392.72 | H25: =O24 -> 176361.03 | I25: ='Parcelas Mensais'!I25 -> 6455.85 | J25: ='Parcelas Mensais'!J25 -> 0.0067005776 | L25: =O25 -> 174968.31 | N25: =O25 -> 174968.31 | O25: =H25-IF(G25="",0,G25) -> 174968.31 | P25: ='Parcelas Mensais'!P25 -> 33.289335 | Q25: ='Parcelas Mensais'!Q25 -> 2.1970961
B26: 16 | C26: 2022 | D26: JUL | E26: ='Parcelas Mensais'!E26 -> 44783 | F26: =H26/105 -> 1666.3649 | G26: ='Parcelas Mensais'!G26 -> 1392.72 | H26: =O25 -> 174968.31 | I26: ='Parcelas Mensais'!I26 -> 6411.95 | J26: ='Parcelas Mensais'!J26 -> -0.0068000341 | L26: =O26 -> 173575.59 | N26: =O26 -> 173575.59 | O26: =H26-IF(G26="",0,G26) -> 173575.59 | P26: ='Parcelas Mensais'!P26 -> 33.289335 | Q26: ='Parcelas Mensais'!Q26 -> 16.478221
B27: 17 | C27: 2022 | D27: AGO | E27: ='Parcelas Mensais'!E27 -> 44844 | F27: =H27/104 -> 1668.9961 | G27: ='Parcelas Mensais'!G27 -> 1392.72 | H27: =O26 -> 173575.59 | I27: ='Parcelas Mensais'!I27 -> 6388.87 | J27: ='Parcelas Mensais'!J27 -> -0.003599529 | L27: =O27 -> 172182.87 | N27: =O27 -> 172182.87 | O27: =H27-IF(G27="",0,G27) -> 172182.87 | P27: ='Parcelas Mensais'!P27 -> 33.289335 | Q27: ='Parcelas Mensais'!Q27 -> 33.505716
B28: 18 | C28: 2022 | D28: SET | E28: ='Parcelas Mensais'!E28 -> 44876 | F28: =H28/103 -> 1671.6783 | G28: ='Parcelas Mensais'!G28 -> 1392.72 | H28: =O27 -> 172182.87 | I28: ='Parcelas Mensais'!I28 -> 6370.34 | J28: ='Parcelas Mensais'!J28 -> -0.0029003564 | L28: =O28 -> 170790.15 | N28: =O28 -> 170790.15 | O28: =H28-IF(G28="",0,G28) -> 170790.15 | P28: ='Parcelas Mensais'!P28 -> 33.289335 | Q28: ='Parcelas Mensais'!Q28 -> 32.956442
B29: 19 | C29: 2022 | D29: OUT | E29: ='Parcelas Mensais'!E29 -> 44908 | F29: =H29/102 -> 1674.4132 | G29: ='Parcelas Mensais'!G29 -> 1351.05 | H29: =O28 -> 170790.15 | I29: ='Parcelas Mensais'!I29 -> 6407.93 | J29: ='Parcelas Mensais'!J29 -> 0.0059007839 | L29: =O29 -> 169439.1 | N29: =O29 -> 169439.1 | O29: =H29-IF(G29="",0,G29) -> 169439.1 | P29: ='Parcelas Mensais'!P29 -> 33.289335 | Q29: ='Parcelas Mensais'!Q29 -> 35.153538 | S29: ='Parcelas Mensais'!S29 -> 5000
B30: 20 | C30: 2022 | D30: NOV | E30: ='Parcelas Mensais'!E30 -> 44937 | F30: =H30/101 -> 1677.6149 | G30: ='Parcelas Mensais'!G30 -> 1392.72 | H30: =O29 -> 169439.1 | I30: ='Parcelas Mensais'!I30 -> 6434.2 | J30: ='Parcelas Mensais'!J30 -> 0.0040996078 | L30: =O30 -> 168046.38 | N30: =O30 -> 168046.38 | O30: =H30-IF(G30="",0,G30) -> 168046.38 | P30: ='Parcelas Mensais'!P30 -> 33.289335 | Q30: ='Parcelas Mensais'!Q30 -> 34.05499
B31: 21 | C31: 2022 | D31: DEZ | E31: ='Parcelas Mensais'!E31 -> 44968 | F31: =H31/100 -> 1680.4638 | G31: ='Parcelas Mensais'!G31 -> 1500 | H31: =O30 -> 168046.38 | I31: ='Parcelas Mensais'!I31 -> 6474.09 | J31: ='Parcelas Mensais'!J31 -> 0.0061996829 | L31: =O31 -> 166546.38 | N31: =O31 -> 166546.38 | O31: =H31-IF(G31="",0,G31) -> 166546.38 | P31: ='Parcelas Mensais'!P31 -> 33.289335 | Q31: ='Parcelas Mensais'!Q31 -> 33.505716
B32: 22 | C32: 2023 | D32: JAN | E32: ='Parcelas Mensais'!E32 -> 44998 | F32: =H32/99 -> 1682.2867 | G32: ='Parcelas Mensais'!G32 -> 2000 | H32: =O31 -> 166546.38 | I32: ='Parcelas Mensais'!I32 -> 6508.4 | J32: ='Parcelas Mensais'!J32 -> 0.0052995865 | L32: =O32 -> 164546.38 | N32: =O32 -> 164546.38 | O32: =H32-IF(G32="",0,G32) -> 164546.38 | P32: ='Parcelas Mensais'!P32 -> 33.289335 | Q32: ='Parcelas Mensais'!Q32 -> 34.05499
B33: 23 | C33: 2023 | D33: FEV | E33: ='Parcelas Mensais'!E33 -> 45028 | F33: =H33/98 -> 1679.0447 | G33: ='Parcelas Mensais'!G33 -> 1500 | H33: =O32 -> 164546.38 | I33: ='Parcelas Mensais'!I33 -> 6563.07 | J33: ='Parcelas Mensais'!J33 -> 0.008399914 | L33: =O33 -> 163046.38 | N33: =O33 -> 163046.38 | O33: =H33-IF(G33="",0,G33) -> 163046.38 | P33: ='Parcelas Mensais'!P33 -> 33.289335 | Q33: ='Parcelas Mensais'!Q33 -> 33.505716
B34: 24 | C34: 2023 | D34: MAR | E34: ='Parcelas Mensais'!E34 -> 45056 | F34: =H34/97 -> 1680.8905 | G34: ='Parcelas Mensais'!G34 -> 1500 | H34: =O33 -> 163046.38 | I34: ='Parcelas Mensais'!I34 -> 6609.67 | J34: ='Parcelas Mensais'!J34 -> 0.0071003357 | K34: 0.046507 | L34: 169059.41 | M34: 18073.46 | N34: =L34+M34 -> 187132.87 | O34: =H34-IF(G34="",0,G34) -> 161546.38 | P34: ='Parcelas Mensais'!P34 -> 33.289335 | Q34: ='Parcelas Mensais'!Q34 -> 33.505716
B35: 25 | C35: 2023 | D35: ABR | E35: ='Parcelas Mensais'!E35 -> 45085 | F35: =H35/96 -> 1949.3007 | G35: ='Parcelas Mensais'!G35 -> 1500 | H35: =N34 -> 187132.87 | I35: ='Parcelas Mensais'!I35 -> 6649.99 | J35: ='Parcelas Mensais'!J35 -> 0.0061001533 | L35: =O35 -> 185632.87 | N35: =O35 -> 185632.87 | O35: =H35-IF(G35="",0,G35) -> 185632.87 | P35: ='Parcelas Mensais'!P35 -> 38.561899 | Q35: ='Parcelas Mensais'!Q35 -> 37.540009 | R35: =Reajustes!I22 -> 46335.44
B36: 26 | C36: 2023 | D36: MAI | E36: ='Parcelas Mensais'!E36 -> 45118 | F36: =H36/95 -> 1954.0302 | G36: ='Parcelas Mensais'!G36 -> 1500 | H36: =O35 -> 185632.87 | I36: ='Parcelas Mensais'!I36 -> 6665.28 | J36: ='Parcelas Mensais'!J36 -> 0.0022992516 | L36: =O36 -> 184132.87 | N36: =O36 -> 184132.87 | O36: =H36-IF(G36="",0,G36) -> 184132.87 | P36: ='Parcelas Mensais'!P36 -> 38.561899 | Q36: ='Parcelas Mensais'!Q36 -> 39.448823
B37: 27 | C37: 2023 | D37: JUN | E37: ='Parcelas Mensais'!E37 -> 45148 | F37: =H37/94 -> 1958.8603 | G37: ='Parcelas Mensais'!G37 -> 1500 | H37: =O36 -> 184132.87 | I37: ='Parcelas Mensais'!I37 -> 6659.95 | J37: ='Parcelas Mensais'!J37 -> -0.00079966633 | L37: =O37 -> 182632.87 | N37: =O37 -> 182632.87 | O37: =H37-IF(G37="",0,G37) -> 182632.87 | P37: ='Parcelas Mensais'!P37 -> 38.561899 | Q37: ='Parcelas Mensais'!Q37 -> 37.540009
B38: 28 | C38: 2023 | D38: JUL | E38: ='Parcelas Mensais'!E38 -> 45182 | F38: =H38/93 -> 1963.7943 | G38: ='Parcelas Mensais'!G38 -> 1500 | H38: =O37 -> 182632.87 | I38: ='Parcelas Mensais'!I38 -> 6667.94 | J38: ='Parcelas Mensais'!J38 -> 0.0011997087 | L38: =O38 -> 181132.87 | N38: =O38 -> 181132.87 | O38: =H38-IF(G38="",0,G38) -> 181132.87 | P38: ='Parcelas Mensais'!P38 -> 38.561899 | Q38: ='Parcelas Mensais'!Q38 -> 41.357637
B39: 29 | C39: 2023 | D39: AGO | E39: ='Parcelas Mensais'!E39 -> 0 | F39: =H39/92 -> 1968.8355 | G39: ='Parcelas Mensais'!G39 -> 0 | H39: =O38 -> 181132.87 | I39: ='Parcelas Mensais'!I39 -> 6683.28 | J39: ='Parcelas Mensais'!J39 -> 0.0023005606 | L39: =O39 -> 181132.87 | N39: =O39 -> 181132.87 | O39: =H39-IF(G39="",0,G39) -> 181132.87 | P39: ='Parcelas Mensais'!P39 -> 0 | Q39: ='Parcelas Mensais'!Q39 -> 0
B40: 30 | C40: 2023 | D40: SET | E40: ='Parcelas Mensais'!E40 -> 0 | F40: =H40/91 -> 1990.4711 | G40: ='Parcelas Mensais'!G40 -> 0 | H40: =O39 -> 181132.87 | I40: ='Parcelas Mensais'!I40 -> 6700.66 | J40: ='Parcelas Mensais'!J40 -> 0.0026005195 | L40: =O40 -> 181132.87 | N40: =O40 -> 181132.87 | O40: =H40-IF(G40="",0,G40) -> 181132.87 | P40: ='Parcelas Mensais'!P40 -> 0 | Q40: ='Parcelas Mensais'!Q40 -> 0
B41: 31 | C41: 2023 | D41: OUT | E41: ='Parcelas Mensais'!E41 -> 0 | F41: =H41/90 -> 2012.5874 | G41: ='Parcelas Mensais'!G41 -> 0 | H41: =O40 -> 181132.87 | I41: ='Parcelas Mensais'!I41 -> 6716.74 | J41: ='Parcelas Mensais'!J41 -> 0.0023997636 | L41: =O41 -> 181132.87 | N41: =O41 -> 181132.87 | O41: =H41-IF(G41="",0,G41) -> 181132.87 | P41: ='Parcelas Mensais'!P41 -> 0 | Q41: ='Parcelas Mensais'!Q41 -> 0
B42: 32 | C42: 2023 | D42: NOV | E42: ='Parcelas Mensais'!E42 -> 0 | F42: =H42/89 -> 2035.2008 | G42: ='Parcelas Mensais'!G42 -> 0 | H42: =O41 -> 181132.87 | I42: ='Parcelas Mensais'!I42 -> 6735.55 | J42: ='Parcelas Mensais'!J42 -> 0.0028004657 | L42: =O42 -> 181132.87 | N42: =O42 -> 181132.87 | O42: =H42-IF(G42="",0,G42) -> 181132.87 | P42: ='Parcelas Mensais'!P42 -> 0 | Q42: ='Parcelas Mensais'!Q42 -> 0
B43: 33 | C43: 2023 | D43: DEZ | E43: ='Parcelas Mensais'!E43 -> 0 | F43: =H43/88 -> 2058.3281 | G43: ='Parcelas Mensais'!G43 -> 0 | H43: =O42 -> 181132.87 | I43: ='Parcelas Mensais'!I43 -> 6773.27 | J43: ='Parcelas Mensais'!J43 -> 0.0056001366 | L43: =O43 -> 181132.87 | N43: =O43 -> 181132.87 | O43: =H43-IF(G43="",0,G43) -> 181132.87 | P43: ='Parcelas Mensais'!P43 -> 0 | Q43: ='Parcelas Mensais'!Q43 -> 0
B44: 34 | C44: 2024 | D44: JAN | E44: ='Parcelas Mensais'!E44 -> 0 | F44: =H44/87 -> 2081.987 | G44: ='Parcelas Mensais'!G44 -> 0 | H44: =O43 -> 181132.87 | I44: ='Parcelas Mensais'!I44 -> 6801.72 | J44: ='Parcelas Mensais'!J44 -> 0.0042003346 | L44: =O44 -> 181132.87 | N44: =O44 -> 181132.87 | O44: =H44-IF(G44="",0,G44) -> 181132.87 | P44: ='Parcelas Mensais'!P44 -> 0 | Q44: ='Parcelas Mensais'!Q44 -> 0
B45: 35 | C45: 2024 | D45: FEV | E45: ='Parcelas Mensais'!E45 -> 0 | F45: =H45/86 -> 2106.1962 | G45: ='Parcelas Mensais'!G45 -> 0 | H45: =O44 -> 181132.87 | I45: ='Parcelas Mensais'!I45 -> 6858.17 | J45: ='Parcelas Mensais'!J45 -> 0.0082993713 | L45: =O45 -> 181132.87 | N45: =O45 -> 181132.87 | O45: =H45-IF(G45="",0,G45) -> 181132.87 | P45: ='Parcelas Mensais'!P45 -> 0 | Q45: ='Parcelas Mensais'!Q45 -> 0
B46: 36 | C46: 2024 | D46: MAR | E46: ='Parcelas Mensais'!E46 -> 0 | F46: =H46/85 -> 2130.9749 | G46: ='Parcelas Mensais'!G46 -> 0 | H46: =O45 -> 181132.87 | I46: ='Parcelas Mensais'!I46 -> 6869.14 | J46: ='Parcelas Mensais'!J46 -> 0.0015995521 | K46: 0.039256 | L46: 188243.41 | M46: 20124.35 | N46: =L46+M46 -> 208367.76 | O46: =H46-IF(G46="",0,G46) -> 181132.87 | P46: ='Parcelas Mensais'!P46 -> 0 | Q46: ='Parcelas Mensais'!Q46 -> 0
B47: 37 | C47: 2024 | D47: ABR | E47: ='Parcelas Mensais'!E47 -> 0 | F47: =H47/84 -> 2480.5686 | G47: ='Parcelas Mensais'!G47 -> 0 | H47: =N46 -> 208367.76 | I47: ='Parcelas Mensais'!I47 -> 6895.24 | J47: ='Parcelas Mensais'!J47 -> 0.0037996023 | L47: =O47 -> 208367.76 | N47: =O47 -> 208367.76 | O47: =H47-IF(G47="",0,G47) -> 208367.76 | P47: ='Parcelas Mensais'!P47 -> 0 | Q47: ='Parcelas Mensais'!Q47 -> 0 | R47: =Reajustes!I23 -> 53302.394
B48: 38 | C48: 2024 | D48: MAI | E48: ='Parcelas Mensais'!E48 -> 0 | F48: =H48/83 -> 2510.4549 | G48: ='Parcelas Mensais'!G48 -> 0 | H48: =O47 -> 208367.76 | I48: ='Parcelas Mensais'!I48 -> 6926.96 | J48: ='Parcelas Mensais'!J48 -> 0.004600275 | L48: =O48 -> 208367.76 | N48: =O48 -> 208367.76 | O48: =H48-IF(G48="",0,G48) -> 208367.76 | P48: ='Parcelas Mensais'!P48 -> 0 | Q48: ='Parcelas Mensais'!Q48 -> 0
B49: 39 | C49: 2024 | D49: JUN | E49: ='Parcelas Mensais'!E49 -> 0 | F49: =H49/82 -> 2541.0702 | G49: ='Parcelas Mensais'!G49 -> 0 | H49: =O48 -> 208367.76 | I49: ='Parcelas Mensais'!I49 -> 6941.51 | J49: ='Parcelas Mensais'!J49 -> 0.0021004885 | L49: =O49 -> 208367.76 | N49: =O49 -> 208367.76 | O49: =H49-IF(G49="",0,G49) -> 208367.76 | P49: ='Parcelas Mensais'!P49 -> 0 | Q49: ='Parcelas Mensais'!Q49 -> 0
B50: 40 | C50: 2024 | D50: JUL | E50: ='Parcelas Mensais'!E50 -> 0 | F50: =H50/81 -> 2572.4415 | G50: ='Parcelas Mensais'!G50 -> 0 | H50: =O49 -> 208367.76 | I50: ='Parcelas Mensais'!I50 -> 6967.89 | J50: ='Parcelas Mensais'!J50 -> 0.0038003259 | L50: =O50 -> 208367.76 | N50: =O50 -> 208367.76 | O50: =H50-IF(G50="",0,G50) -> 208367.76 | P50: ='Parcelas Mensais'!P50 -> 0 | Q50: ='Parcelas Mensais'!Q50 -> 0
B51: 41 | C51: 2024 | D51: AGO | E51: ='Parcelas Mensais'!E51 -> 0 | F51: =H51/80 -> 2604.597 | G51: ='Parcelas Mensais'!G51 -> 0 | H51: =O50 -> 208367.76 | I51: ='Parcelas Mensais'!I51 -> 6966.5 | J51: ='Parcelas Mensais'!J51 -> -0.0001994865 | L51: =O51 -> 208367.76 | N51: =O51 -> 208367.76 | O51: =H51-IF(G51="",0,G51) -> 208367.76 | P51: ='Parcelas Mensais'!P51 -> 0 | Q51: ='Parcelas Mensais'!Q51 -> 0
B52: 42 | C52: 2024 | D52: SET | E52: ='Parcelas Mensais'!E52 -> 0 | F52: =H52/79 -> 2637.5666 | G52: ='Parcelas Mensais'!G52 -> 0 | H52: =O51 -> 208367.76 | I52: ='Parcelas Mensais'!I52 -> 6997.15 | J52: ='Parcelas Mensais'!J52 -> 0.0043996268 | L52: =O52 -> 208367.76 | N52: =O52 -> 208367.76 | O52: =H52-IF(G52="",0,G52) -> 208367.76 | P52: ='Parcelas Mensais'!P52 -> 0 | Q52: ='Parcelas Mensais'!Q52 -> 0
B53: 43 | C53: 2024 | D53: OUT | E53: ='Parcelas Mensais'!E53 -> 0 | F53: =H53/78 -> 2671.3815 | G53: ='Parcelas Mensais'!G53 -> 0 | H53: =O52 -> 208367.76 | I53: ='Parcelas Mensais'!I53 -> 7036.33 | J53: ='Parcelas Mensais'!J53 -> 0.0055994226 | L53: =O53 -> 208367.76 | N53: =O53 -> 208367.76 | O53: =H53-IF(G53="",0,G53) -> 208367.76 | P53: ='Parcelas Mensais'!P53 -> 0 | Q53: ='Parcelas Mensais'!Q53 -> 0
B54: 44 | C54: 2024 | D54: NOV | E54: ='Parcelas Mensais'!E54 -> 0 | F54: =H54/77 -> 2706.0748 | G54: ='Parcelas Mensais'!G54 -> 0 | H54: =O53 -> 208367.76 | I54: ='Parcelas Mensais'!I54 -> 7063.77 | J54: ='Parcelas Mensais'!J54 -> 0.0038997602 | L54: =O54 -> 208367.76 | N54: =O54 -> 208367.76 | O54: =H54-IF(G54="",0,G54) -> 208367.76 | P54: ='Parcelas Mensais'!P54 -> 0 | Q54: ='Parcelas Mensais'!Q54 -> 0
B55: 45 | C55: 2024 | D55: DEZ | E55: ='Parcelas Mensais'!E55 -> 0 | F55: =H55/76 -> 2741.6811 | G55: ='Parcelas Mensais'!G55 -> 0 | H55: =O54 -> 208367.76 | I55: ='Parcelas Mensais'!I55 -> 7100.5 | J55: ='Parcelas Mensais'!J55 -> 0.0051997729 | L55: =O55 -> 208367.76 | N55: =O55 -> 208367.76 | O55: =H55-IF(G55="",0,G55) -> 208367.76 | P55: ='Parcelas Mensais'!P55 -> 0 | Q55: ='Parcelas Mensais'!Q55 -> 0
B56: 46 | C56: 2025 | D56: JAN | E56: ='Parcelas Mensais'!E56 -> 0 | F56: =H56/75 -> 2778.2368 | G56: ='Parcelas Mensais'!G56 -> 0 | H56: =O55 -> 208367.76 | I56: ='Parcelas Mensais'!I56 -> 7111.86 | J56: ='Parcelas Mensais'!J56 -> 0.0015998873 | L56: =O56 -> 208367.76 | N56: =O56 -> 208367.76 | O56: =H56-IF(G56="",0,G56) -> 208367.76 | P56: ='Parcelas Mensais'!P56 -> 0 | Q56: ='Parcelas Mensais'!Q56 -> 0
B57: 47 | C57: 2025 | D57: FEV | E57: ='Parcelas Mensais'!E57 -> 0 | F57: =H57/74 -> 2815.7805 | G57: ='Parcelas Mensais'!G57 -> 0 | H57: =O56 -> 208367.76 | I57: ='Parcelas Mensais'!I57 -> 7205.03 | J57: ='Parcelas Mensais'!J57 -> 0.013100652 | L57: =O57 -> 208367.76 | N57: =O57 -> 208367.76 | O57: =H57-IF(G57="",0,G57) -> 208367.76 | P57: ='Parcelas Mensais'!P57 -> 0 | Q57: ='Parcelas Mensais'!Q57 -> 0
B58: 48 | C58: 2025 | D58: MAR | E58: ='Parcelas Mensais'!E58 -> 0 | F58: =H58/73 -> 2854.3529 | G58: ='Parcelas Mensais'!G58 -> 0 | H58: =O57 -> 208367.76 | I58: ='Parcelas Mensais'!I58 -> 7245.38 | J58: ='Parcelas Mensais'!J58 -> 0.0056002543 | K58: 0.054772 | L58: 219780.46 | M58: 23495.84 | N58: =L58+M58 -> 243276.3 | O58: =H58-IF(G58="",0,G58) -> 208367.76 | P58: ='Parcelas Mensais'!P58 -> 0 | Q58: ='Parcelas Mensais'!Q58 -> 0
B59: 49 | C59: 2025 | D59: ABR | E59: ='Parcelas Mensais'!E59 -> 0 | F59: =H59/72 -> 3378.8375 | G59: ='Parcelas Mensais'!G59 -> 0 | H59: =N58 -> 243276.3 | I59: ='Parcelas Mensais'!I59 -> 7276.53 | J59: ='Parcelas Mensais'!J59 -> 0.0042992914 | L59: =O59 -> 243276.3 | N59: =O59 -> 243276.3 | O59: =H59-IF(G59="",0,G59) -> 243276.3 | P59: ='Parcelas Mensais'!P59 -> 0 | Q59: ='Parcelas Mensais'!Q59 -> 0 | R59: =Reajustes!I24 -> 62232.37
B60: 50 | C60: 2025 | D60: MAI | E60: ='Parcelas Mensais'!E60 -> 0 | F60: =H60/71 -> 3426.4268 | G60: ='Parcelas Mensais'!G60 -> 0 | H60: =O59 -> 243276.3 | I60: ='Parcelas Mensais'!I60 -> 7295.45 | J60: ='Parcelas Mensais'!J60 -> 0.0026001405 | L60: =O60 -> 243276.3 | N60: =O60 -> 243276.3 | O60: =H60-IF(G60="",0,G60) -> 243276.3 | P60: ='Parcelas Mensais'!P60 -> 0 | Q60: ='Parcelas Mensais'!Q60 -> 0
B61: 51 | C61: 2025 | D61: JUN | E61: ='Parcelas Mensais'!E61 -> 0 | F61: =H61/70 -> 3475.3757 | G61: ='Parcelas Mensais'!G61 -> 0 | H61: =O60 -> 243276.3 | I61: ='Parcelas Mensais'!I61 -> 7312.96 | J61: ='Parcelas Mensais'!J61 -> 0.0024001261 | L61: =O61 -> 243276.3 | N61: =O61 -> 243276.3 | O61: =H61-IF(G61="",0,G61) -> 243276.3 | P61: ='Parcelas Mensais'!P61 -> 0 | Q61: ='Parcelas Mensais'!Q61 -> 0
B62: 52 | C62: 2025 | D62: JUL | E62: ='Parcelas Mensais'!E62 -> 0 | F62: =H62/69 -> 3525.7435 | G62: ='Parcelas Mensais'!G62 -> 0 | H62: =O61 -> 243276.3 | I62: ='Parcelas Mensais'!I62 -> 7331.97 | J62: ='Parcelas Mensais'!J62 -> 0.0025994946 | L62: =O62 -> 243276.3 | N62: =O62 -> 243276.3 | O62: =H62-IF(G62="",0,G62) -> 243276.3 | P62: ='Parcelas Mensais'!P62 -> 0 | Q62: ='Parcelas Mensais'!Q62 -> 0
B63: 53 | C63: 2025 | D63: AGO | E63: ='Parcelas Mensais'!E63 -> 0 | F63: =H63/68 -> 3577.5926 | G63: ='Parcelas Mensais'!G63 -> 0 | H63: =O62 -> 243276.3 | I63: ='Parcelas Mensais'!I63 -> 7323.91 | J63: ='Parcelas Mensais'!J63 -> -0.0010992953 | L63: =O63 -> 243276.3 | N63: =O63 -> 243276.3 | O63: =H63-IF(G63="",0,G63) -> 243276.3 | P63: ='Parcelas Mensais'!P63 -> 0 | Q63: ='Parcelas Mensais'!Q63 -> 0
B64: 54 | C64: 2025 | D64: SET | E64: ='Parcelas Mensais'!E64 -> 0 | F64: =H64/67 -> 3630.9896 | G64: ='Parcelas Mensais'!G64 -> 0 | H64: =O63 -> 243276.3 | I64: ='Parcelas Mensais'!I64 -> 7359.06 | J64: ='Parcelas Mensais'!J64 -> 0.004799349 | L64: =O64 -> 243276.3 | N64: =O64 -> 243276.3 | O64: =H64-IF(G64="",0,G64) -> 243276.3 | P64: ='Parcelas Mensais'!P64 -> 0 | Q64: ='Parcelas Mensais'!Q64 -> 0
B65: 55 | C65: 2025 | D65: OUT | E65: ='Parcelas Mensais'!E65 -> 0 | F65: =H65/66 -> 3686.0045 | G65: ='Parcelas Mensais'!G65 -> 0 | H65: =O64 -> 243276.3 | I65: ='Parcelas Mensais'!I65 -> 7365.69 | J65: ='Parcelas Mensais'!J65 -> 0.00090093028 | L65: =O65 -> 243276.3 | N65: =O65 -> 243276.3 | O65: =H65-IF(G65="",0,G65) -> 243276.3 | P65: ='Parcelas Mensais'!P65 -> 0 | Q65: ='Parcelas Mensais'!Q65 -> 0
B66: 56 | C66: 2025 | D66: NOV | E66: ='Parcelas Mensais'!E66 -> 0 | F66: =H66/65 -> 3742.7123 | G66: ='Parcelas Mensais'!G66 -> 0 | H66: =O65 -> 243276.3 | I66: ='Parcelas Mensais'!I66 -> 7378.94 | J66: ='Parcelas Mensais'!J66 -> 0.001798881 | L66: =O66 -> 243276.3 | N66: =O66 -> 243276.3 | O66: =H66-IF(G66="",0,G66) -> 243276.3 | P66: ='Parcelas Mensais'!P66 -> 0 | Q66: ='Parcelas Mensais'!Q66 -> 0
B67: 57 | C67: 2025 | D67: DEZ | E67: ='Parcelas Mensais'!E67 -> 0 | F67: =H67/64 -> 3801.1922 | G67: ='Parcelas Mensais'!G67 -> 0 | H67: =O66 -> 243276.3 | I67: ='Parcelas Mensais'!I67 -> 7403.29 | J67: ='Parcelas Mensais'!J67 -> 0.003299932 | L67: =O67 -> 243276.3 | N67: =O67 -> 243276.3 | O67: =H67-IF(G67="",0,G67) -> 243276.3 | P67: ='Parcelas Mensais'!P67 -> 0 | Q67: ='Parcelas Mensais'!Q67 -> 0
B68: 58 | C68: 2026 | D68: JAN | E68: ='Parcelas Mensais'!E68 -> 0 | F68: =H68/63 -> 3861.5286 | G68: ='Parcelas Mensais'!G68 -> 0 | H68: =O67 -> 243276.3 | I68: ='Parcelas Mensais'!I68 -> 7427.73 | J68: ='Parcelas Mensais'!J68 -> 0.003301235 | L68: =O68 -> 243276.3 | N68: =O68 -> 243276.3 | O68: =H68-IF(G68="",0,G68) -> 243276.3 | P68: ='Parcelas Mensais'!P68 -> 0 | Q68: ='Parcelas Mensais'!Q68 -> 0
B69: 59 | C69: 2026 | D69: FEV | E69: ='Parcelas Mensais'!E69 -> 0 | F69: =H69/62 -> 3923.8113 | G69: ='Parcelas Mensais'!G69 -> 0 | H69: =O68 -> 243276.3 | I69: ='Parcelas Mensais'!I69 -> 7479.72 | J69: ='Parcelas Mensais'!J69 -> 0.0069994467 | L69: =O69 -> 243276.3 | N69: =O69 -> 243276.3 | O69: =H69-IF(G69="",0,G69) -> 243276.3 | P69: ='Parcelas Mensais'!P69 -> 0 | Q69: ='Parcelas Mensais'!Q69 -> 0
B70: 60 | C70: 2026 | D70: MAR | E70: ='Parcelas Mensais'!E70 -> 0 | F70: =H70/61 -> 3988.1361 | G70: ='Parcelas Mensais'!G70 -> 0 | H70: =O69 -> 243276.3 | I70: ='Parcelas Mensais'!I70 -> 7545.54 | J70: ='Parcelas Mensais'!J70 -> 0.0087997946 | K70: 0.041428 | L70: 253354.86 | M70: 27085.15 | N70: =L70+M70 -> 280440.01 | O70: =H70-IF(G70="",0,G70) -> 243276.3 | P70: ='Parcelas Mensais'!P70 -> 0 | Q70: ='Parcelas Mensais'!Q70 -> 0
B71: 61 | C71: 2026 | D71: ABR | E71: ='Parcelas Mensais'!E71 -> 0 | F71: =H71/60 -> 4674.0002 | G71: ='Parcelas Mensais'!G71 -> 0 | H71: =N70 -> 280440.01 | I71: ='Parcelas Mensais'!I71 -> 0 | J71: ='Parcelas Mensais'!J71 -> 0 | L71: =O71 -> 280440.01 | N71: =O71 -> 280440.01 | O71: =H71-IF(G71="",0,G71) -> 280440.01 | P71: ='Parcelas Mensais'!P71 -> 0 | Q71: ='Parcelas Mensais'!Q71 -> 0 | R71: =Reajustes!I25 -> 71739.167
B72: 62 | C72: 2026 | D72: MAI | E72: ='Parcelas Mensais'!E72 -> 0 | F72: =H72/59 -> 4753.2205 | G72: ='Parcelas Mensais'!G72 -> 0 | H72: =O71 -> 280440.01 | I72: ='Parcelas Mensais'!I72 -> 0 | J72: ='Parcelas Mensais'!J72 -> 0 | L72: =O72 -> 280440.01 | N72: =O72 -> 280440.01 | O72: =H72-IF(G72="",0,G72) -> 280440.01 | P72: ='Parcelas Mensais'!P72 -> 0 | Q72: ='Parcelas Mensais'!Q72 -> 0
B73: 63 | C73: 2026 | D73: JUN | E73: ='Parcelas Mensais'!E73 -> 0 | F73: =H73/58 -> 4835.1726 | G73: ='Parcelas Mensais'!G73 -> 0 | H73: =O72 -> 280440.01 | I73: ='Parcelas Mensais'!I73 -> 0 | J73: ='Parcelas Mensais'!J73 -> 0 | L73: =O73 -> 280440.01 | N73: =O73 -> 280440.01 | O73: =H73-IF(G73="",0,G73) -> 280440.01 | P73: ='Parcelas Mensais'!P73 -> 0 | Q73: ='Parcelas Mensais'!Q73 -> 0
B74: 64 | C74: 2026 | D74: JUL | E74: ='Parcelas Mensais'!E74 -> 0 | F74: =H74/57 -> 4920.0002 | G74: ='Parcelas Mensais'!G74 -> 0 | H74: =O73 -> 280440.01 | I74: ='Parcelas Mensais'!I74 -> 0 | J74: ='Parcelas Mensais'!J74 -> 0 | L74: =O74 -> 280440.01 | N74: =O74 -> 280440.01 | O74: =H74-IF(G74="",0,G74) -> 280440.01 | P74: ='Parcelas Mensais'!P74 -> 0 | Q74: ='Parcelas Mensais'!Q74 -> 0
B75: 65 | C75: 2026 | D75: AGO | E75: ='Parcelas Mensais'!E75 -> 0 | F75: =H75/56 -> 5007.8573 | G75: ='Parcelas Mensais'!G75 -> 0 | H75: =O74 -> 280440.01 | I75: ='Parcelas Mensais'!I75 -> 0 | J75: ='Parcelas Mensais'!J75 -> 0 | L75: =O75 -> 280440.01 | N75: =O75 -> 280440.01 | O75: =H75-IF(G75="",0,G75) -> 280440.01 | P75: ='Parcelas Mensais'!P75 -> 0 | Q75: ='Parcelas Mensais'!Q75 -> 0
B76: 66 | C76: 2026 | D76: SET | E76: ='Parcelas Mensais'!E76 -> 0 | F76: =H76/55 -> 5098.9093 | G76: ='Parcelas Mensais'!G76 -> 0 | H76: =O75 -> 280440.01 | I76: ='Parcelas Mensais'!I76 -> 0 | J76: ='Parcelas Mensais'!J76 -> 0 | L76: =O76 -> 280440.01 | N76: =O76 -> 280440.01 | O76: =H76-IF(G76="",0,G76) -> 280440.01 | P76: ='Parcelas Mensais'!P76 -> 0 | Q76: ='Parcelas Mensais'!Q76 -> 0
B77: 67 | C77: 2026 | D77: OUT | E77: ='Parcelas Mensais'!E77 -> 0 | F77: =H77/54 -> 5193.3335 | G77: ='Parcelas Mensais'!G77 -> 0 | H77: =O76 -> 280440.01 | I77: ='Parcelas Mensais'!I77 -> 0 | J77: ='Parcelas Mensais'!J77 -> 0 | L77: =O77 -> 280440.01 | N77: =O77 -> 280440.01 | O77: =H77-IF(G77="",0,G77) -> 280440.01 | P77: ='Parcelas Mensais'!P77 -> 0 | Q77: ='Parcelas Mensais'!Q77 -> 0
B78: 68 | C78: 2026 | D78: NOV | E78: ='Parcelas Mensais'!E78 -> 0 | F78: =H78/53 -> 5291.3209 | G78: ='Parcelas Mensais'!G78 -> 0 | H78: =O77 -> 280440.01 | I78: ='Parcelas Mensais'!I78 -> 0 | J78: ='Parcelas Mensais'!J78 -> 0 | L78: =O78 -> 280440.01 | N78: =O78 -> 280440.01 | O78: =H78-IF(G78="",0,G78) -> 280440.01 | P78: ='Parcelas Mensais'!P78 -> 0 | Q78: ='Parcelas Mensais'!Q78 -> 0
B79: 69 | C79: 2026 | D79: DEZ | E79: ='Parcelas Mensais'!E79 -> 0 | F79: =H79/52 -> 5393.0771 | G79: ='Parcelas Mensais'!G79 -> 0 | H79: =O78 -> 280440.01 | I79: ='Parcelas Mensais'!I79 -> 0 | J79: ='Parcelas Mensais'!J79 -> 0 | L79: =O79 -> 280440.01 | N79: =O79 -> 280440.01 | O79: =H79-IF(G79="",0,G79) -> 280440.01 | P79: ='Parcelas Mensais'!P79 -> 0 | Q79: ='Parcelas Mensais'!Q79 -> 0
B80: 70 | C80: 2027 | D80: JAN | E80: ='Parcelas Mensais'!E80 -> 0 | F80: =H80/51 -> 5498.8237 | G80: ='Parcelas Mensais'!G80 -> 0 | H80: =O79 -> 280440.01 | I80: ='Parcelas Mensais'!I80 -> 0 | J80: ='Parcelas Mensais'!J80 -> 0 | L80: =O80 -> 280440.01 | N80: =O80 -> 280440.01 | O80: =H80-IF(G80="",0,G80) -> 280440.01 | P80: ='Parcelas Mensais'!P80 -> 0 | Q80: ='Parcelas Mensais'!Q80 -> 0
B81: 71 | C81: 2027 | D81: FEV | E81: ='Parcelas Mensais'!E81 -> 0 | F81: =H81/50 -> 5608.8002 | G81: ='Parcelas Mensais'!G81 -> 0 | H81: =O80 -> 280440.01 | I81: ='Parcelas Mensais'!I81 -> 0 | J81: ='Parcelas Mensais'!J81 -> 0 | L81: =O81 -> 280440.01 | N81: =O81 -> 280440.01 | O81: =H81-IF(G81="",0,G81) -> 280440.01 | P81: ='Parcelas Mensais'!P81 -> 0 | Q81: ='Parcelas Mensais'!Q81 -> 0
B82: 72 | C82: 2027 | D82: MAR | E82: ='Parcelas Mensais'!E82 -> 0 | F82: =H82/49 -> 5723.2655 | G82: ='Parcelas Mensais'!G82 -> 0 | H82: =O81 -> 280440.01 | I82: ='Parcelas Mensais'!I82 -> 0 | J82: ='Parcelas Mensais'!J82 -> 0 | K82: 0 | L82: =ROUND(O82*(1+K82),2) -> 280440.01 | M82: =ROUND(L82*10.6906/100,2) -> 29980.72 | N82: =L82+M82 -> 310420.73 | O82: =H82-IF(G82="",0,G82) -> 280440.01 | P82: ='Parcelas Mensais'!P82 -> 0 | Q82: ='Parcelas Mensais'!Q82 -> 0
B83: 73 | C83: 2027 | D83: ABR | E83: ='Parcelas Mensais'!E83 -> 0 | F83: =H83/48 -> 6467.0985 | G83: ='Parcelas Mensais'!G83 -> 0 | H83: =N82 -> 310420.73 | I83: ='Parcelas Mensais'!I83 -> 0 | J83: ='Parcelas Mensais'!J83 -> 0 | L83: =O83 -> 310420.73 | N83: =O83 -> 310420.73 | O83: =H83-IF(G83="",0,G83) -> 310420.73 | P83: ='Parcelas Mensais'!P83 -> 0 | Q83: ='Parcelas Mensais'!Q83 -> 0 | R83: =Reajustes!I26 -> 79408.531
B84: 74 | C84: 2027 | D84: MAI | E84: ='Parcelas Mensais'!E84 -> 0 | F84: =H84/47 -> 6604.6964 | G84: ='Parcelas Mensais'!G84 -> 0 | H84: =O83 -> 310420.73 | I84: ='Parcelas Mensais'!I84 -> 0 | J84: ='Parcelas Mensais'!J84 -> 0 | L84: =O84 -> 310420.73 | N84: =O84 -> 310420.73 | O84: =H84-IF(G84="",0,G84) -> 310420.73 | P84: ='Parcelas Mensais'!P84 -> 0 | Q84: ='Parcelas Mensais'!Q84 -> 0
B85: 75 | C85: 2027 | D85: JUN | E85: ='Parcelas Mensais'!E85 -> 0 | F85: =H85/46 -> 6748.2767 | G85: ='Parcelas Mensais'!G85 -> 0 | H85: =O84 -> 310420.73 | I85: ='Parcelas Mensais'!I85 -> 0 | J85: ='Parcelas Mensais'!J85 -> 0 | L85: =O85 -> 310420.73 | N85: =O85 -> 310420.73 | O85: =H85-IF(G85="",0,G85) -> 310420.73 | P85: ='Parcelas Mensais'!P85 -> 0 | Q85: ='Parcelas Mensais'!Q85 -> 0
B86: 76 | C86: 2027 | D86: JUL | E86: ='Parcelas Mensais'!E86 -> 0 | F86: =H86/45 -> 6898.2384 | G86: ='Parcelas Mensais'!G86 -> 0 | H86: =O85 -> 310420.73 | I86: ='Parcelas Mensais'!I86 -> 0 | J86: ='Parcelas Mensais'!J86 -> 0 | L86: =O86 -> 310420.73 | N86: =O86 -> 310420.73 | O86: =H86-IF(G86="",0,G86) -> 310420.73 | P86: ='Parcelas Mensais'!P86 -> 0 | Q86: ='Parcelas Mensais'!Q86 -> 0
B87: 77 | C87: 2027 | D87: AGO | E87: ='Parcelas Mensais'!E87 -> 0 | F87: =H87/44 -> 7055.0166 | G87: ='Parcelas Mensais'!G87 -> 0 | H87: =O86 -> 310420.73 | I87: ='Parcelas Mensais'!I87 -> 0 | J87: ='Parcelas Mensais'!J87 -> 0 | L87: =O87 -> 310420.73 | N87: =O87 -> 310420.73 | O87: =H87-IF(G87="",0,G87) -> 310420.73 | P87: ='Parcelas Mensais'!P87 -> 0 | Q87: ='Parcelas Mensais'!Q87 -> 0
B88: 78 | C88: 2027 | D88: SET | E88: ='Parcelas Mensais'!E88 -> 0 | F88: =H88/43 -> 7219.0867 | G88: ='Parcelas Mensais'!G88 -> 0 | H88: =O87 -> 310420.73 | I88: ='Parcelas Mensais'!I88 -> 0 | J88: ='Parcelas Mensais'!J88 -> 0 | L88: =O88 -> 310420.73 | N88: =O88 -> 310420.73 | O88: =H88-IF(G88="",0,G88) -> 310420.73 | P88: ='Parcelas Mensais'!P88 -> 0 | Q88: ='Parcelas Mensais'!Q88 -> 0
B89: 79 | C89: 2027 | D89: OUT | E89: ='Parcelas Mensais'!E89 -> 0 | F89: =H89/42 -> 7390.9698 | G89: ='Parcelas Mensais'!G89 -> 0 | H89: =O88 -> 310420.73 | I89: ='Parcelas Mensais'!I89 -> 0 | J89: ='Parcelas Mensais'!J89 -> 0 | L89: =O89 -> 310420.73 | N89: =O89 -> 310420.73 | O89: =H89-IF(G89="",0,G89) -> 310420.73 | P89: ='Parcelas Mensais'!P89 -> 0 | Q89: ='Parcelas Mensais'!Q89 -> 0
B90: 80 | C90: 2027 | D90: NOV | E90: ='Parcelas Mensais'!E90 -> 0 | F90: =H90/41 -> 7571.2373 | G90: ='Parcelas Mensais'!G90 -> 0 | H90: =O89 -> 310420.73 | I90: ='Parcelas Mensais'!I90 -> 0 | J90: ='Parcelas Mensais'!J90 -> 0 | L90: =O90 -> 310420.73 | N90: =O90 -> 310420.73 | O90: =H90-IF(G90="",0,G90) -> 310420.73 | P90: ='Parcelas Mensais'!P90 -> 0 | Q90: ='Parcelas Mensais'!Q90 -> 0
B91: 81 | C91: 2027 | D91: DEZ | E91: ='Parcelas Mensais'!E91 -> 0 | F91: =H91/40 -> 7760.5183 | G91: ='Parcelas Mensais'!G91 -> 0 | H91: =O90 -> 310420.73 | I91: ='Parcelas Mensais'!I91 -> 0 | J91: ='Parcelas Mensais'!J91 -> 0 | L91: =O91 -> 310420.73 | N91: =O91 -> 310420.73 | O91: =H91-IF(G91="",0,G91) -> 310420.73 | P91: ='Parcelas Mensais'!P91 -> 0 | Q91: ='Parcelas Mensais'!Q91 -> 0
B92: 82 | C92: 2028 | D92: JAN | E92: ='Parcelas Mensais'!E92 -> 0 | F92: =H92/39 -> 7959.5059 | G92: ='Parcelas Mensais'!G92 -> 0 | H92: =O91 -> 310420.73 | I92: ='Parcelas Mensais'!I92 -> 0 | J92: ='Parcelas Mensais'!J92 -> 0 | L92: =O92 -> 310420.73 | N92: =O92 -> 310420.73 | O92: =H92-IF(G92="",0,G92) -> 310420.73 | P92: ='Parcelas Mensais'!P92 -> 0 | Q92: ='Parcelas Mensais'!Q92 -> 0
B93: 83 | C93: 2028 | D93: FEV | E93: ='Parcelas Mensais'!E93 -> 0 | F93: =H93/38 -> 8168.9666 | G93: ='Parcelas Mensais'!G93 -> 0 | H93: =O92 -> 310420.73 | I93: ='Parcelas Mensais'!I93 -> 0 | J93: ='Parcelas Mensais'!J93 -> 0 | L93: =O93 -> 310420.73 | N93: =O93 -> 310420.73 | O93: =H93-IF(G93="",0,G93) -> 310420.73 | P93: ='Parcelas Mensais'!P93 -> 0 | Q93: ='Parcelas Mensais'!Q93 -> 0
B94: 84 | C94: 2028 | D94: MAR | E94: ='Parcelas Mensais'!E94 -> 0 | F94: =H94/37 -> 8389.7495 | G94: ='Parcelas Mensais'!G94 -> 0 | H94: =O93 -> 310420.73 | I94: ='Parcelas Mensais'!I94 -> 0 | J94: ='Parcelas Mensais'!J94 -> 0 | K94: 0 | L94: =ROUND(O94*(1+K94),2) -> 310420.73 | M94: =ROUND(L94*10.6906/100,2) -> 33185.84 | N94: =L94+M94 -> 343606.57 | O94: =H94-IF(G94="",0,G94) -> 310420.73 | P94: ='Parcelas Mensais'!P94 -> 0 | Q94: ='Parcelas Mensais'!Q94 -> 0
B95: 85 | C95: 2028 | D95: ABR | E95: ='Parcelas Mensais'!E95 -> 0 | F95: =H95/36 -> 9544.6269 | G95: ='Parcelas Mensais'!G95 -> 0 | H95: =N94 -> 343606.57 | I95: ='Parcelas Mensais'!I95 -> 0 | J95: ='Parcelas Mensais'!J95 -> 0 | L95: =O95 -> 343606.57 | N95: =O95 -> 343606.57 | O95: =H95-IF(G95="",0,G95) -> 343606.57 | P95: ='Parcelas Mensais'!P95 -> 0 | Q95: ='Parcelas Mensais'!Q95 -> 0 | R95: =Reajustes!I27 -> 87897.797
B96: 86 | C96: 2028 | D96: MAI | E96: ='Parcelas Mensais'!E96 -> 0 | F96: =H96/35 -> 9817.3306 | G96: ='Parcelas Mensais'!G96 -> 0 | H96: =O95 -> 343606.57 | I96: ='Parcelas Mensais'!I96 -> 0 | J96: ='Parcelas Mensais'!J96 -> 0 | L96: =O96 -> 343606.57 | N96: =O96 -> 343606.57 | O96: =H96-IF(G96="",0,G96) -> 343606.57 | P96: ='Parcelas Mensais'!P96 -> 0 | Q96: ='Parcelas Mensais'!Q96 -> 0
B97: 87 | C97: 2028 | D97: JUN | E97: ='Parcelas Mensais'!E97 -> 0 | F97: =H97/34 -> 10106.076 | G97: ='Parcelas Mensais'!G97 -> 0 | H97: =O96 -> 343606.57 | I97: ='Parcelas Mensais'!I97 -> 0 | J97: ='Parcelas Mensais'!J97 -> 0 | L97: =O97 -> 343606.57 | N97: =O97 -> 343606.57 | O97: =H97-IF(G97="",0,G97) -> 343606.57 | P97: ='Parcelas Mensais'!P97 -> 0 | Q97: ='Parcelas Mensais'!Q97 -> 0
B98: 88 | C98: 2028 | D98: JUL | E98: ='Parcelas Mensais'!E98 -> 0 | F98: =H98/33 -> 10412.32 | G98: ='Parcelas Mensais'!G98 -> 0 | H98: =O97 -> 343606.57 | I98: ='Parcelas Mensais'!I98 -> 0 | J98: ='Parcelas Mensais'!J98 -> 0 | L98: =O98 -> 343606.57 | N98: =O98 -> 343606.57 | O98: =H98-IF(G98="",0,G98) -> 343606.57 | P98: ='Parcelas Mensais'!P98 -> 0 | Q98: ='Parcelas Mensais'!Q98 -> 0
B99: 89 | C99: 2028 | D99: AGO | E99: ='Parcelas Mensais'!E99 -> 0 | F99: =H99/32 -> 10737.705 | G99: ='Parcelas Mensais'!G99 -> 0 | H99: =O98 -> 343606.57 | I99: ='Parcelas Mensais'!I99 -> 0 | J99: ='Parcelas Mensais'!J99 -> 0 | L99: =O99 -> 343606.57 | N99: =O99 -> 343606.57 | O99: =H99-IF(G99="",0,G99) -> 343606.57 | P99: ='Parcelas Mensais'!P99 -> 0 | Q99: ='Parcelas Mensais'!Q99 -> 0
B100: 90 | C100: 2028 | D100: SET | E100: ='Parcelas Mensais'!E100 -> 0 | F100: =H100/31 -> 11084.083 | G100: ='Parcelas Mensais'!G100 -> 0 | H100: =O99 -> 343606.57 | I100: ='Parcelas Mensais'!I100 -> 0 | J100: ='Parcelas Mensais'!J100 -> 0 | L100: =O100 -> 343606.57 | N100: =O100 -> 343606.57 | O100: =H100-IF(G100="",0,G100) -> 343606.57 | P100: ='Parcelas Mensais'!P100 -> 0 | Q100: ='Parcelas Mensais'!Q100 -> 0
B101: 91 | C101: 2028 | D101: OUT | E101: ='Parcelas Mensais'!E101 -> 0 | F101: =H101/30 -> 11453.552 | G101: ='Parcelas Mensais'!G101 -> 0 | H101: =O100 -> 343606.57 | I101: ='Parcelas Mensais'!I101 -> 0 | J101: ='Parcelas Mensais'!J101 -> 0 | L101: =O101 -> 343606.57 | N101: =O101 -> 343606.57 | O101: =H101-IF(G101="",0,G101) -> 343606.57 | P101: ='Parcelas Mensais'!P101 -> 0 | Q101: ='Parcelas Mensais'!Q101 -> 0
...
